[{"arguments":["clang","-Wno-documentation-unknown-command","-Wno-unknown-warning-option","-Wno-unknown-pragmas","-nostdinc","-nostdinc++","-g","-std=gnu++2a","-Wall","-Wextra","-Wextra","-fexceptions","-mthreads","-fsyntax-only","-m64","--target=x86_64-w64-mingw32","-DUNICODE","-D_UNICODE","-DWIN32","-DMINGW_HAS_SECURE_API","-DQT_QML_DEBUG","-DQT_WIDGETS_LIB","-DQT_GUI_LIB","-DQT_CONCURRENT_LIB","-DQT_SERIALPORT_LIB","-DQT_CORE_LIB","-DQT_NEEDS_QMAIN","-DQ_CREATOR_RUN","-IC:\\Qt\\Tools\\QtCreator\\share\\qtcreator\\cplusplus\\wrappedMingwHeaders","-IC:\\Qt\\Tools\\QtCreator\\share\\qtcreator\\cplusplus\\wrappedQtHeaders","-IC:\\Qt\\Tools\\QtCreator\\share\\qtcreator\\cplusplus\\wrappedQtHeaders\\QtCore","-ID:\\Repos\\AlgoDemon\\project\\source","-ID:\\Repos\\AlgoDemon\\external_src","-ID:\\Repos\\AlgoDemon\\external_src\\external\\Qt-Advanced-Docking-System-master\\src","-ID:\\Repos\\AlgoDemon\\external_src\\camera_module\\include","-ID:\\Repos\\AlgoDemon\\external_src\\camera_module\\include\\CameraSDK_include","-IC:\\Qt\\6.4.2\\mingw_64\\include","-IC:\\Qt\\6.4.2\\mingw_64\\include\\QtWidgets","-IC:\\Qt\\6.4.2\\mingw_64\\include\\QtGui","-IC:\\Qt\\6.4.2\\mingw_64\\include\\QtConcurrent","-IC:\\Qt\\6.4.2\\mingw_64\\include\\QtSerialPort","-IC:\\Qt\\6.4.2\\mingw_64\\include\\QtCore","-ID:\\Repos\\AlgoDemon\\project\\build-AlgoDemon-Desktop_Qt_6_4_2_MinGW_64_bit-Debug\\debug","-ID:\\Repos\\AlgoDemon\\project\\build-AlgoDemon-Desktop_Qt_6_4_2_MinGW_64_bit-Debug","-IC:\\Qt\\6.4.2\\mingw_64\\mkspecs\\win32-g++","-isystem","C:\\Qt\\Tools\\mingw1120_64\\lib\\gcc\\x86_64-w64-mingw32\\11.2.0\\include\\c++","-isystem","C:\\Qt\\Tools\\mingw1120_64\\lib\\gcc\\x86_64-w64-mingw32\\11.2.0\\include\\c++\\x86_64-w64-mingw32","-isystem","C:\\Qt\\Tools\\mingw1120_64\\lib\\gcc\\x86_64-w64-mingw32\\11.2.0\\include\\c++\\backward","-isystem","C:\\Qt\\Tools\\QtCreator\\bin\\clang\\lib\\clang\\15.0.0\\include","-isystem","C:\\Qt\\Tools\\mingw1120_64\\x86_64-w64-mingw32\\include","-fmessage-length=0","-fdiagnostics-show-note-include-stack","-fretain-comments-from-system-headers","-fmacro-backtrace-limit=0","-ferror-limit=1000","-x","c++","D:\\Repos\\AlgoDemon\\project\\source\\appprocessor.cpp"],"directory":"D:/Repos/AlgoDemon/project/build-AlgoDemon-Desktop_Qt_6_4_2_MinGW_64_bit-Debug/.qtc_clangd","file":"D:/Repos/AlgoDemon/project/source/appprocessor.cpp"},{"arguments":["clang","-Wno-documentation-unknown-command","-Wno-unknown-warning-option","-Wno-unknown-pragmas","-nostdinc","-nostdinc++","-g","-std=gnu++2a","-Wall","-Wextra","-Wextra","-fexceptions","-mthreads","-fsyntax-only","-m64","--target=x86_64-w64-mingw32","-DUNICODE","-D_UNICODE","-DWIN32","-DMINGW_HAS_SECURE_API","-DQT_QML_DEBUG","-DQT_WIDGETS_LIB","-DQT_GUI_LIB","-DQT_CONCURRENT_LIB","-DQT_SERIALPORT_LIB","-DQT_CORE_LIB","-DQT_NEEDS_QMAIN","-DQ_CREATOR_RUN","-IC:\\Qt\\Tools\\QtCreator\\share\\qtcreator\\cplusplus\\wrappedMingwHeaders","-IC:\\Qt\\Tools\\QtCreator\\share\\qtcreator\\cplusplus\\wrappedQtHeaders","-IC:\\Qt\\Tools\\QtCreator\\share\\qtcreator\\cplusplus\\wrappedQtHeaders\\QtCore","-ID:\\Repos\\AlgoDemon\\project\\source","-ID:\\Repos\\AlgoDemon\\external_src","-ID:\\Repos\\AlgoDemon\\external_src\\external\\Qt-Advanced-Docking-System-master\\src","-ID:\\Repos\\AlgoDemon\\external_src\\camera_module\\include","-ID:\\Repos\\AlgoDemon\\external_src\\camera_module\\include\\CameraSDK_include","-IC:\\Qt\\6.4.2\\mingw_64\\include","-IC:\\Qt\\6.4.2\\mingw_64\\include\\QtWidgets","-IC:\\Qt\\6.4.2\\mingw_64\\include\\QtGui","-IC:\\Qt\\6.4.2\\mingw_64\\include\\QtConcurrent","-IC:\\Qt\\6.4.2\\mingw_64\\include\\QtSerialPort","-IC:\\Qt\\6.4.2\\mingw_64\\include\\QtCore","-ID:\\Repos\\AlgoDemon\\project\\build-AlgoDemon-Desktop_Qt_6_4_2_MinGW_64_bit-Debug\\debug","-ID:\\Repos\\AlgoDemon\\project\\build-AlgoDemon-Desktop_Qt_6_4_2_MinGW_64_bit-Debug","-IC:\\Qt\\6.4.2\\mingw_64\\mkspecs\\win32-g++","-isystem","C:\\Qt\\Tools\\mingw1120_64\\lib\\gcc\\x86_64-w64-mingw32\\11.2.0\\include\\c++","-isystem","C:\\Qt\\Tools\\mingw1120_64\\lib\\gcc\\x86_64-w64-mingw32\\11.2.0\\include\\c++\\x86_64-w64-mingw32","-isystem","C:\\Qt\\Tools\\mingw1120_64\\lib\\gcc\\x86_64-w64-mingw32\\11.2.0\\include\\c++\\backward","-isystem","C:\\Qt\\Tools\\QtCreator\\bin\\clang\\lib\\clang\\15.0.0\\include","-isystem","C:\\Qt\\Tools\\mingw1120_64\\x86_64-w64-mingw32\\include","-fmessage-length=0","-fdiagnostics-show-note-include-stack","-fretain-comments-from-system-headers","-fmacro-backtrace-limit=0","-ferror-limit=1000","-x","c++","D:\\Repos\\AlgoDemon\\project\\source\\camerathread.cpp"],"directory":"D:/Repos/AlgoDemon/project/build-AlgoDemon-Desktop_Qt_6_4_2_MinGW_64_bit-Debug/.qtc_clangd","file":"D:/Repos/AlgoDemon/project/source/camerathread.cpp"},{"arguments":["clang","-Wno-documentation-unknown-command","-Wno-unknown-warning-option","-Wno-unknown-pragmas","-nostdinc","-nostdinc++","-g","-std=gnu++2a","-Wall","-Wextra","-Wextra","-fexceptions","-mthreads","-fsyntax-only","-m64","--target=x86_64-w64-mingw32","-DUNICODE","-D_UNICODE","-DWIN32","-DMINGW_HAS_SECURE_API","-DQT_QML_DEBUG","-DQT_WIDGETS_LIB","-DQT_GUI_LIB","-DQT_CONCURRENT_LIB","-DQT_SERIALPORT_LIB","-DQT_CORE_LIB","-DQT_NEEDS_QMAIN","-DQ_CREATOR_RUN","-IC:\\Qt\\Tools\\QtCreator\\share\\qtcreator\\cplusplus\\wrappedMingwHeaders","-IC:\\Qt\\Tools\\QtCreator\\share\\qtcreator\\cplusplus\\wrappedQtHeaders","-IC:\\Qt\\Tools\\QtCreator\\share\\qtcreator\\cplusplus\\wrappedQtHeaders\\QtCore","-ID:\\Repos\\AlgoDemon\\project\\source","-ID:\\Repos\\AlgoDemon\\external_src","-ID:\\Repos\\AlgoDemon\\external_src\\external\\Qt-Advanced-Docking-System-master\\src","-ID:\\Repos\\AlgoDemon\\external_src\\camera_module\\include","-ID:\\Repos\\AlgoDemon\\external_src\\camera_module\\include\\CameraSDK_include","-IC:\\Qt\\6.4.2\\mingw_64\\include","-IC:\\Qt\\6.4.2\\mingw_64\\include\\QtWidgets","-IC:\\Qt\\6.4.2\\mingw_64\\include\\QtGui","-IC:\\Qt\\6.4.2\\mingw_64\\include\\QtConcurrent","-IC:\\Qt\\6.4.2\\mingw_64\\include\\QtSerialPort","-IC:\\Qt\\6.4.2\\mingw_64\\include\\QtCore","-ID:\\Repos\\AlgoDemon\\project\\build-AlgoDemon-Desktop_Qt_6_4_2_MinGW_64_bit-Debug\\debug","-ID:\\Repos\\AlgoDemon\\project\\build-AlgoDemon-Desktop_Qt_6_4_2_MinGW_64_bit-Debug","-IC:\\Qt\\6.4.2\\mingw_64\\mkspecs\\win32-g++","-isystem","C:\\Qt\\Tools\\mingw1120_64\\lib\\gcc\\x86_64-w64-mingw32\\11.2.0\\include\\c++","-isystem","C:\\Qt\\Tools\\mingw1120_64\\lib\\gcc\\x86_64-w64-mingw32\\11.2.0\\include\\c++\\x86_64-w64-mingw32","-isystem","C:\\Qt\\Tools\\mingw1120_64\\lib\\gcc\\x86_64-w64-mingw32\\11.2.0\\include\\c++\\backward","-isystem","C:\\Qt\\Tools\\QtCreator\\bin\\clang\\lib\\clang\\15.0.0\\include","-isystem","C:\\Qt\\Tools\\mingw1120_64\\x86_64-w64-mingw32\\include","-fmessage-length=0","-fdiagnostics-show-note-include-stack","-fretain-comments-from-system-headers","-fmacro-backtrace-limit=0","-ferror-limit=1000","-x","c++","D:\\Repos\\AlgoDemon\\project\\source\\main.cpp"],"directory":"D:/Repos/AlgoDemon/project/build-AlgoDemon-Desktop_Qt_6_4_2_MinGW_64_bit-Debug/.qtc_clangd","file":"D:/Repos/AlgoDemon/project/source/main.cpp"},{"arguments":["clang","-Wno-documentation-unknown-command","-Wno-unknown-warning-option","-Wno-unknown-pragmas","-nostdinc","-nostdinc++","-g","-std=gnu++2a","-Wall","-Wextra","-Wextra","-fexceptions","-mthreads","-fsyntax-only","-m64","--target=x86_64-w64-mingw32","-DUNICODE","-D_UNICODE","-DWIN32","-DMINGW_HAS_SECURE_API","-DQT_QML_DEBUG","-DQT_WIDGETS_LIB","-DQT_GUI_LIB","-DQT_CONCURRENT_LIB","-DQT_SERIALPORT_LIB","-DQT_CORE_LIB","-DQT_NEEDS_QMAIN","-DQ_CREATOR_RUN","-IC:\\Qt\\Tools\\QtCreator\\share\\qtcreator\\cplusplus\\wrappedMingwHeaders","-IC:\\Qt\\Tools\\QtCreator\\share\\qtcreator\\cplusplus\\wrappedQtHeaders","-IC:\\Qt\\Tools\\QtCreator\\share\\qtcreator\\cplusplus\\wrappedQtHeaders\\QtCore","-ID:\\Repos\\AlgoDemon\\project\\source","-ID:\\Repos\\AlgoDemon\\external_src","-ID:\\Repos\\AlgoDemon\\external_src\\external\\Qt-Advanced-Docking-System-master\\src","-ID:\\Repos\\AlgoDemon\\external_src\\camera_module\\include","-ID:\\Repos\\AlgoDemon\\external_src\\camera_module\\include\\CameraSDK_include","-IC:\\Qt\\6.4.2\\mingw_64\\include","-IC:\\Qt\\6.4.2\\mingw_64\\include\\QtWidgets","-IC:\\Qt\\6.4.2\\mingw_64\\include\\QtGui","-IC:\\Qt\\6.4.2\\mingw_64\\include\\QtConcurrent","-IC:\\Qt\\6.4.2\\mingw_64\\include\\QtSerialPort","-IC:\\Qt\\6.4.2\\mingw_64\\include\\QtCore","-ID:\\Repos\\AlgoDemon\\project\\build-AlgoDemon-Desktop_Qt_6_4_2_MinGW_64_bit-Debug\\debug","-ID:\\Repos\\AlgoDemon\\project\\build-AlgoDemon-Desktop_Qt_6_4_2_MinGW_64_bit-Debug","-IC:\\Qt\\6.4.2\\mingw_64\\mkspecs\\win32-g++","-isystem","C:\\Qt\\Tools\\mingw1120_64\\lib\\gcc\\x86_64-w64-mingw32\\11.2.0\\include\\c++","-isystem","C:\\Qt\\Tools\\mingw1120_64\\lib\\gcc\\x86_64-w64-mingw32\\11.2.0\\include\\c++\\x86_64-w64-mingw32","-isystem","C:\\Qt\\Tools\\mingw1120_64\\lib\\gcc\\x86_64-w64-mingw32\\11.2.0\\include\\c++\\backward","-isystem","C:\\Qt\\Tools\\QtCreator\\bin\\clang\\lib\\clang\\15.0.0\\include","-isystem","C:\\Qt\\Tools\\mingw1120_64\\x86_64-w64-mingw32\\include","-fmessage-length=0","-fdiagnostics-show-note-include-stack","-fretain-comments-from-system-headers","-fmacro-backtrace-limit=0","-ferror-limit=1000","-x","c++","D:\\Repos\\AlgoDemon\\project\\source\\mainwindow.cpp"],"directory":"D:/Repos/AlgoDemon/project/build-AlgoDemon-Desktop_Qt_6_4_2_MinGW_64_bit-Debug/.qtc_clangd","file":"D:/Repos/AlgoDemon/project/source/mainwindow.cpp"},{"arguments":["clang","-Wno-documentation-unknown-command","-Wno-unknown-warning-option","-Wno-unknown-pragmas","-nostdinc","-nostdinc++","-g","-std=gnu++2a","-Wall","-Wextra","-Wextra","-fexceptions","-mthreads","-fsyntax-only","-m64","--target=x86_64-w64-mingw32","-DUNICODE","-D_UNICODE","-DWIN32","-DMINGW_HAS_SECURE_API","-DQT_QML_DEBUG","-DQT_WIDGETS_LIB","-DQT_GUI_LIB","-DQT_CONCURRENT_LIB","-DQT_SERIALPORT_LIB","-DQT_CORE_LIB","-DQT_NEEDS_QMAIN","-DQ_CREATOR_RUN","-IC:\\Qt\\Tools\\QtCreator\\share\\qtcreator\\cplusplus\\wrappedMingwHeaders","-IC:\\Qt\\Tools\\QtCreator\\share\\qtcreator\\cplusplus\\wrappedQtHeaders","-IC:\\Qt\\Tools\\QtCreator\\share\\qtcreator\\cplusplus\\wrappedQtHeaders\\QtCore","-ID:\\Repos\\AlgoDemon\\project\\source","-ID:\\Repos\\AlgoDemon\\external_src","-ID:\\Repos\\AlgoDemon\\external_src\\external\\Qt-Advanced-Docking-System-master\\src","-ID:\\Repos\\AlgoDemon\\external_src\\camera_module\\include","-ID:\\Repos\\AlgoDemon\\external_src\\camera_module\\include\\CameraSDK_include","-IC:\\Qt\\6.4.2\\mingw_64\\include","-IC:\\Qt\\6.4.2\\mingw_64\\include\\QtWidgets","-IC:\\Qt\\6.4.2\\mingw_64\\include\\QtGui","-IC:\\Qt\\6.4.2\\mingw_64\\include\\QtConcurrent","-IC:\\Qt\\6.4.2\\mingw_64\\include\\QtSerialPort","-IC:\\Qt\\6.4.2\\mingw_64\\include\\QtCore","-ID:\\Repos\\AlgoDemon\\project\\build-AlgoDemon-Desktop_Qt_6_4_2_MinGW_64_bit-Debug\\debug","-ID:\\Repos\\AlgoDemon\\project\\build-AlgoDemon-Desktop_Qt_6_4_2_MinGW_64_bit-Debug","-IC:\\Qt\\6.4.2\\mingw_64\\mkspecs\\win32-g++","-isystem","C:\\Qt\\Tools\\mingw1120_64\\lib\\gcc\\x86_64-w64-mingw32\\11.2.0\\include\\c++","-isystem","C:\\Qt\\Tools\\mingw1120_64\\lib\\gcc\\x86_64-w64-mingw32\\11.2.0\\include\\c++\\x86_64-w64-mingw32","-isystem","C:\\Qt\\Tools\\mingw1120_64\\lib\\gcc\\x86_64-w64-mingw32\\11.2.0\\include\\c++\\backward","-isystem","C:\\Qt\\Tools\\QtCreator\\bin\\clang\\lib\\clang\\15.0.0\\include","-isystem","C:\\Qt\\Tools\\mingw1120_64\\x86_64-w64-mingw32\\include","-fmessage-length=0","-fdiagnostics-show-note-include-stack","-fretain-comments-from-system-headers","-fmacro-backtrace-limit=0","-ferror-limit=1000","-x","c++","D:\\Repos\\AlgoDemon\\project\\source\\mattoqimage.cpp"],"directory":"D:/Repos/AlgoDemon/project/build-AlgoDemon-Desktop_Qt_6_4_2_MinGW_64_bit-Debug/.qtc_clangd","file":"D:/Repos/AlgoDemon/project/source/mattoqimage.cpp"},{"arguments":["clang","-Wno-documentation-unknown-command","-Wno-unknown-warning-option","-Wno-unknown-pragmas","-nostdinc","-nostdinc++","-g","-std=gnu++2a","-Wall","-Wextra","-Wextra","-fexceptions","-mthreads","-fsyntax-only","-m64","--target=x86_64-w64-mingw32","-DUNICODE","-D_UNICODE","-DWIN32","-DMINGW_HAS_SECURE_API","-DQT_QML_DEBUG","-DQT_WIDGETS_LIB","-DQT_GUI_LIB","-DQT_CONCURRENT_LIB","-DQT_SERIALPORT_LIB","-DQT_CORE_LIB","-DQT_NEEDS_QMAIN","-DQ_CREATOR_RUN","-IC:\\Qt\\Tools\\QtCreator\\share\\qtcreator\\cplusplus\\wrappedMingwHeaders","-IC:\\Qt\\Tools\\QtCreator\\share\\qtcreator\\cplusplus\\wrappedQtHeaders","-IC:\\Qt\\Tools\\QtCreator\\share\\qtcreator\\cplusplus\\wrappedQtHeaders\\QtCore","-ID:\\Repos\\AlgoDemon\\project\\source","-ID:\\Repos\\AlgoDemon\\external_src","-ID:\\Repos\\AlgoDemon\\external_src\\external\\Qt-Advanced-Docking-System-master\\src","-ID:\\Repos\\AlgoDemon\\external_src\\camera_module\\include","-ID:\\Repos\\AlgoDemon\\external_src\\camera_module\\include\\CameraSDK_include","-IC:\\Qt\\6.4.2\\mingw_64\\include","-IC:\\Qt\\6.4.2\\mingw_64\\include\\QtWidgets","-IC:\\Qt\\6.4.2\\mingw_64\\include\\QtGui","-IC:\\Qt\\6.4.2\\mingw_64\\include\\QtConcurrent","-IC:\\Qt\\6.4.2\\mingw_64\\include\\QtSerialPort","-IC:\\Qt\\6.4.2\\mingw_64\\include\\QtCore","-ID:\\Repos\\AlgoDemon\\project\\build-AlgoDemon-Desktop_Qt_6_4_2_MinGW_64_bit-Debug\\debug","-ID:\\Repos\\AlgoDemon\\project\\build-AlgoDemon-Desktop_Qt_6_4_2_MinGW_64_bit-Debug","-IC:\\Qt\\6.4.2\\mingw_64\\mkspecs\\win32-g++","-isystem","C:\\Qt\\Tools\\mingw1120_64\\lib\\gcc\\x86_64-w64-mingw32\\11.2.0\\include\\c++","-isystem","C:\\Qt\\Tools\\mingw1120_64\\lib\\gcc\\x86_64-w64-mingw32\\11.2.0\\include\\c++\\x86_64-w64-mingw32","-isystem","C:\\Qt\\Tools\\mingw1120_64\\lib\\gcc\\x86_64-w64-mingw32\\11.2.0\\include\\c++\\backward","-isystem","C:\\Qt\\Tools\\QtCreator\\bin\\clang\\lib\\clang\\15.0.0\\include","-isystem","C:\\Qt\\Tools\\mingw1120_64\\x86_64-w64-mingw32\\include","-fmessage-length=0","-fdiagnostics-show-note-include-stack","-fretain-comments-from-system-headers","-fmacro-backtrace-limit=0","-ferror-limit=1000","-x","c++","D:\\Repos\\AlgoDemon\\project\\source\\objectivethread.cpp"],"directory":"D:/Repos/AlgoDemon/project/build-AlgoDemon-Desktop_Qt_6_4_2_MinGW_64_bit-Debug/.qtc_clangd","file":"D:/Repos/AlgoDemon/project/source/objectivethread.cpp"},{"arguments":["clang","-Wno-documentation-unknown-command","-Wno-unknown-warning-option","-Wno-unknown-pragmas","-nostdinc","-nostdinc++","-g","-std=gnu++2a","-Wall","-Wextra","-Wextra","-fexceptions","-mthreads","-fsyntax-only","-m64","--target=x86_64-w64-mingw32","-DUNICODE","-D_UNICODE","-DWIN32","-DMINGW_HAS_SECURE_API","-DQT_QML_DEBUG","-DQT_WIDGETS_LIB","-DQT_GUI_LIB","-DQT_CONCURRENT_LIB","-DQT_SERIALPORT_LIB","-DQT_CORE_LIB","-DQT_NEEDS_QMAIN","-DQ_CREATOR_RUN","-IC:\\Qt\\Tools\\QtCreator\\share\\qtcreator\\cplusplus\\wrappedMingwHeaders","-IC:\\Qt\\Tools\\QtCreator\\share\\qtcreator\\cplusplus\\wrappedQtHeaders","-IC:\\Qt\\Tools\\QtCreator\\share\\qtcreator\\cplusplus\\wrappedQtHeaders\\QtCore","-ID:\\Repos\\AlgoDemon\\project\\source","-ID:\\Repos\\AlgoDemon\\external_src","-ID:\\Repos\\AlgoDemon\\external_src\\external\\Qt-Advanced-Docking-System-master\\src","-ID:\\Repos\\AlgoDemon\\external_src\\camera_module\\include","-ID:\\Repos\\AlgoDemon\\external_src\\camera_module\\include\\CameraSDK_include","-IC:\\Qt\\6.4.2\\mingw_64\\include","-IC:\\Qt\\6.4.2\\mingw_64\\include\\QtWidgets","-IC:\\Qt\\6.4.2\\mingw_64\\include\\QtGui","-IC:\\Qt\\6.4.2\\mingw_64\\include\\QtConcurrent","-IC:\\Qt\\6.4.2\\mingw_64\\include\\QtSerialPort","-IC:\\Qt\\6.4.2\\mingw_64\\include\\QtCore","-ID:\\Repos\\AlgoDemon\\project\\build-AlgoDemon-Desktop_Qt_6_4_2_MinGW_64_bit-Debug\\debug","-ID:\\Repos\\AlgoDemon\\project\\build-AlgoDemon-Desktop_Qt_6_4_2_MinGW_64_bit-Debug","-IC:\\Qt\\6.4.2\\mingw_64\\mkspecs\\win32-g++","-isystem","C:\\Qt\\Tools\\mingw1120_64\\lib\\gcc\\x86_64-w64-mingw32\\11.2.0\\include\\c++","-isystem","C:\\Qt\\Tools\\mingw1120_64\\lib\\gcc\\x86_64-w64-mingw32\\11.2.0\\include\\c++\\x86_64-w64-mingw32","-isystem","C:\\Qt\\Tools\\mingw1120_64\\lib\\gcc\\x86_64-w64-mingw32\\11.2.0\\include\\c++\\backward","-isystem","C:\\Qt\\Tools\\QtCreator\\bin\\clang\\lib\\clang\\15.0.0\\include","-isystem","C:\\Qt\\Tools\\mingw1120_64\\x86_64-w64-mingw32\\include","-fmessage-length=0","-fdiagnostics-show-note-include-stack","-fretain-comments-from-system-headers","-fmacro-backtrace-limit=0","-ferror-limit=1000","-x","c++","D:\\Repos\\AlgoDemon\\project\\source\\processingthread.cpp"],"directory":"D:/Repos/AlgoDemon/project/build-AlgoDemon-Desktop_Qt_6_4_2_MinGW_64_bit-Debug/.qtc_clangd","file":"D:/Repos/AlgoDemon/project/source/processingthread.cpp"},{"arguments":["clang","-Wno-documentation-unknown-command","-Wno-unknown-warning-option","-Wno-unknown-pragmas","-nostdinc","-nostdinc++","-g","-std=gnu++2a","-Wall","-Wextra","-Wextra","-fexceptions","-mthreads","-fsyntax-only","-m64","--target=x86_64-w64-mingw32","-DUNICODE","-D_UNICODE","-DWIN32","-DMINGW_HAS_SECURE_API","-DQT_QML_DEBUG","-DQT_WIDGETS_LIB","-DQT_GUI_LIB","-DQT_CONCURRENT_LIB","-DQT_SERIALPORT_LIB","-DQT_CORE_LIB","-DQT_NEEDS_QMAIN","-DQ_CREATOR_RUN","-IC:\\Qt\\Tools\\QtCreator\\share\\qtcreator\\cplusplus\\wrappedMingwHeaders","-IC:\\Qt\\Tools\\QtCreator\\share\\qtcreator\\cplusplus\\wrappedQtHeaders","-IC:\\Qt\\Tools\\QtCreator\\share\\qtcreator\\cplusplus\\wrappedQtHeaders\\QtCore","-ID:\\Repos\\AlgoDemon\\project\\source","-ID:\\Repos\\AlgoDemon\\external_src","-ID:\\Repos\\AlgoDemon\\external_src\\external\\Qt-Advanced-Docking-System-master\\src","-ID:\\Repos\\AlgoDemon\\external_src\\camera_module\\include","-ID:\\Repos\\AlgoDemon\\external_src\\camera_module\\include\\CameraSDK_include","-IC:\\Qt\\6.4.2\\mingw_64\\include","-IC:\\Qt\\6.4.2\\mingw_64\\include\\QtWidgets","-IC:\\Qt\\6.4.2\\mingw_64\\include\\QtGui","-IC:\\Qt\\6.4.2\\mingw_64\\include\\QtConcurrent","-IC:\\Qt\\6.4.2\\mingw_64\\include\\QtSerialPort","-IC:\\Qt\\6.4.2\\mingw_64\\include\\QtCore","-ID:\\Repos\\AlgoDemon\\project\\build-AlgoDemon-Desktop_Qt_6_4_2_MinGW_64_bit-Debug\\debug","-ID:\\Repos\\AlgoDemon\\project\\build-AlgoDemon-Desktop_Qt_6_4_2_MinGW_64_bit-Debug","-IC:\\Qt\\6.4.2\\mingw_64\\mkspecs\\win32-g++","-isystem","C:\\Qt\\Tools\\mingw1120_64\\lib\\gcc\\x86_64-w64-mingw32\\11.2.0\\include\\c++","-isystem","C:\\Qt\\Tools\\mingw1120_64\\lib\\gcc\\x86_64-w64-mingw32\\11.2.0\\include\\c++\\x86_64-w64-mingw32","-isystem","C:\\Qt\\Tools\\mingw1120_64\\lib\\gcc\\x86_64-w64-mingw32\\11.2.0\\include\\c++\\backward","-isystem","C:\\Qt\\Tools\\QtCreator\\bin\\clang\\lib\\clang\\15.0.0\\include","-isystem","C:\\Qt\\Tools\\mingw1120_64\\x86_64-w64-mingw32\\include","-fmessage-length=0","-fdiagnostics-show-note-include-stack","-fretain-comments-from-system-headers","-fmacro-backtrace-limit=0","-ferror-limit=1000","-x","c++","D:\\Repos\\AlgoDemon\\external_src\\widgets\\graphicsview.cpp"],"directory":"D:/Repos/AlgoDemon/project/build-AlgoDemon-Desktop_Qt_6_4_2_MinGW_64_bit-Debug/.qtc_clangd","file":"D:/Repos/AlgoDemon/external_src/widgets/graphicsview.cpp"},{"arguments":["clang","-Wno-documentation-unknown-command","-Wno-unknown-warning-option","-Wno-unknown-pragmas","-nostdinc","-nostdinc++","-g","-std=gnu++2a","-Wall","-Wextra","-Wextra","-fexceptions","-mthreads","-fsyntax-only","-m64","--target=x86_64-w64-mingw32","-DUNICODE","-D_UNICODE","-DWIN32","-DMINGW_HAS_SECURE_API","-DQT_QML_DEBUG","-DQT_WIDGETS_LIB","-DQT_GUI_LIB","-DQT_CONCURRENT_LIB","-DQT_SERIALPORT_LIB","-DQT_CORE_LIB","-DQT_NEEDS_QMAIN","-DQ_CREATOR_RUN","-IC:\\Qt\\Tools\\QtCreator\\share\\qtcreator\\cplusplus\\wrappedMingwHeaders","-IC:\\Qt\\Tools\\QtCreator\\share\\qtcreator\\cplusplus\\wrappedQtHeaders","-IC:\\Qt\\Tools\\QtCreator\\share\\qtcreator\\cplusplus\\wrappedQtHeaders\\QtCore","-ID:\\Repos\\AlgoDemon\\project\\source","-ID:\\Repos\\AlgoDemon\\external_src","-ID:\\Repos\\AlgoDemon\\external_src\\external\\Qt-Advanced-Docking-System-master\\src","-ID:\\Repos\\AlgoDemon\\external_src\\camera_module\\include","-ID:\\Repos\\AlgoDemon\\external_src\\camera_module\\include\\CameraSDK_include","-IC:\\Qt\\6.4.2\\mingw_64\\include","-IC:\\Qt\\6.4.2\\mingw_64\\include\\QtWidgets","-IC:\\Qt\\6.4.2\\mingw_64\\include\\QtGui","-IC:\\Qt\\6.4.2\\mingw_64\\include\\QtConcurrent","-IC:\\Qt\\6.4.2\\mingw_64\\include\\QtSerialPort","-IC:\\Qt\\6.4.2\\mingw_64\\include\\QtCore","-ID:\\Repos\\AlgoDemon\\project\\build-AlgoDemon-Desktop_Qt_6_4_2_MinGW_64_bit-Debug\\debug","-ID:\\Repos\\AlgoDemon\\project\\build-AlgoDemon-Desktop_Qt_6_4_2_MinGW_64_bit-Debug","-IC:\\Qt\\6.4.2\\mingw_64\\mkspecs\\win32-g++","-isystem","C:\\Qt\\Tools\\mingw1120_64\\lib\\gcc\\x86_64-w64-mingw32\\11.2.0\\include\\c++","-isystem","C:\\Qt\\Tools\\mingw1120_64\\lib\\gcc\\x86_64-w64-mingw32\\11.2.0\\include\\c++\\x86_64-w64-mingw32","-isystem","C:\\Qt\\Tools\\mingw1120_64\\lib\\gcc\\x86_64-w64-mingw32\\11.2.0\\include\\c++\\backward","-isystem","C:\\Qt\\Tools\\QtCreator\\bin\\clang\\lib\\clang\\15.0.0\\include","-isystem","C:\\Qt\\Tools\\mingw1120_64\\x86_64-w64-mingw32\\include","-fmessage-length=0","-fdiagnostics-show-note-include-stack","-fretain-comments-from-system-headers","-fmacro-backtrace-limit=0","-ferror-limit=1000","-x","c++","D:\\Repos\\AlgoDemon\\external_src\\widgets\\viewportcontroller.cpp"],"directory":"D:/Repos/AlgoDemon/project/build-AlgoDemon-Desktop_Qt_6_4_2_MinGW_64_bit-Debug/.qtc_clangd","file":"D:/Repos/AlgoDemon/external_src/widgets/viewportcontroller.cpp"},{"arguments":["clang","-Wno-documentation-unknown-command","-Wno-unknown-warning-option","-Wno-unknown-pragmas","-nostdinc","-nostdinc++","-g","-std=gnu++2a","-Wall","-Wextra","-Wextra","-fexceptions","-mthreads","-fsyntax-only","-m64","--target=x86_64-w64-mingw32","-DUNICODE","-D_UNICODE","-DWIN32","-DMINGW_HAS_SECURE_API","-DQT_QML_DEBUG","-DQT_WIDGETS_LIB","-DQT_GUI_LIB","-DQT_CONCURRENT_LIB","-DQT_SERIALPORT_LIB","-DQT_CORE_LIB","-DQT_NEEDS_QMAIN","-DQ_CREATOR_RUN","-IC:\\Qt\\Tools\\QtCreator\\share\\qtcreator\\cplusplus\\wrappedMingwHeaders","-IC:\\Qt\\Tools\\QtCreator\\share\\qtcreator\\cplusplus\\wrappedQtHeaders","-IC:\\Qt\\Tools\\QtCreator\\share\\qtcreator\\cplusplus\\wrappedQtHeaders\\QtCore","-ID:\\Repos\\AlgoDemon\\project\\source","-ID:\\Repos\\AlgoDemon\\external_src","-ID:\\Repos\\AlgoDemon\\external_src\\external\\Qt-Advanced-Docking-System-master\\src","-ID:\\Repos\\AlgoDemon\\external_src\\camera_module\\include","-ID:\\Repos\\AlgoDemon\\external_src\\camera_module\\include\\CameraSDK_include","-IC:\\Qt\\6.4.2\\mingw_64\\include","-IC:\\Qt\\6.4.2\\mingw_64\\include\\QtWidgets","-IC:\\Qt\\6.4.2\\mingw_64\\include\\QtGui","-IC:\\Qt\\6.4.2\\mingw_64\\include\\QtConcurrent","-IC:\\Qt\\6.4.2\\mingw_64\\include\\QtSerialPort","-IC:\\Qt\\6.4.2\\mingw_64\\include\\QtCore","-ID:\\Repos\\AlgoDemon\\project\\build-AlgoDemon-Desktop_Qt_6_4_2_MinGW_64_bit-Debug\\debug","-ID:\\Repos\\AlgoDemon\\project\\build-AlgoDemon-Desktop_Qt_6_4_2_MinGW_64_bit-Debug","-IC:\\Qt\\6.4.2\\mingw_64\\mkspecs\\win32-g++","-isystem","C:\\Qt\\Tools\\mingw1120_64\\lib\\gcc\\x86_64-w64-mingw32\\11.2.0\\include\\c++","-isystem","C:\\Qt\\Tools\\mingw1120_64\\lib\\gcc\\x86_64-w64-mingw32\\11.2.0\\include\\c++\\x86_64-w64-mingw32","-isystem","C:\\Qt\\Tools\\mingw1120_64\\lib\\gcc\\x86_64-w64-mingw32\\11.2.0\\include\\c++\\backward","-isystem","C:\\Qt\\Tools\\QtCreator\\bin\\clang\\lib\\clang\\15.0.0\\include","-isystem","C:\\Qt\\Tools\\mingw1120_64\\x86_64-w64-mingw32\\include","-fmessage-length=0","-fdiagnostics-show-note-include-stack","-fretain-comments-from-system-headers","-fmacro-backtrace-limit=0","-ferror-limit=1000","-x","c++","D:\\Repos\\AlgoDemon\\external_src\\camera_module\\src\\camframe.cpp"],"directory":"D:/Repos/AlgoDemon/project/build-AlgoDemon-Desktop_Qt_6_4_2_MinGW_64_bit-Debug/.qtc_clangd","file":"D:/Repos/AlgoDemon/external_src/camera_module/src/camframe.cpp"},{"arguments":["clang","-Wno-documentation-unknown-command","-Wno-unknown-warning-option","-Wno-unknown-pragmas","-nostdinc","-nostdinc++","-g","-std=gnu++2a","-Wall","-Wextra","-Wextra","-fexceptions","-mthreads","-fsyntax-only","-m64","--target=x86_64-w64-mingw32","-DUNICODE","-D_UNICODE","-DWIN32","-DMINGW_HAS_SECURE_API","-DQT_QML_DEBUG","-DQT_WIDGETS_LIB","-DQT_GUI_LIB","-DQT_CONCURRENT_LIB","-DQT_SERIALPORT_LIB","-DQT_CORE_LIB","-DQT_NEEDS_QMAIN","-DQ_CREATOR_RUN","-IC:\\Qt\\Tools\\QtCreator\\share\\qtcreator\\cplusplus\\wrappedMingwHeaders","-IC:\\Qt\\Tools\\QtCreator\\share\\qtcreator\\cplusplus\\wrappedQtHeaders","-IC:\\Qt\\Tools\\QtCreator\\share\\qtcreator\\cplusplus\\wrappedQtHeaders\\QtCore","-ID:\\Repos\\AlgoDemon\\project\\source","-ID:\\Repos\\AlgoDemon\\external_src","-ID:\\Repos\\AlgoDemon\\external_src\\external\\Qt-Advanced-Docking-System-master\\src","-ID:\\Repos\\AlgoDemon\\external_src\\camera_module\\include","-ID:\\Repos\\AlgoDemon\\external_src\\camera_module\\include\\CameraSDK_include","-IC:\\Qt\\6.4.2\\mingw_64\\include","-IC:\\Qt\\6.4.2\\mingw_64\\include\\QtWidgets","-IC:\\Qt\\6.4.2\\mingw_64\\include\\QtGui","-IC:\\Qt\\6.4.2\\mingw_64\\include\\QtConcurrent","-IC:\\Qt\\6.4.2\\mingw_64\\include\\QtSerialPort","-IC:\\Qt\\6.4.2\\mingw_64\\include\\QtCore","-ID:\\Repos\\AlgoDemon\\project\\build-AlgoDemon-Desktop_Qt_6_4_2_MinGW_64_bit-Debug\\debug","-ID:\\Repos\\AlgoDemon\\project\\build-AlgoDemon-Desktop_Qt_6_4_2_MinGW_64_bit-Debug","-IC:\\Qt\\6.4.2\\mingw_64\\mkspecs\\win32-g++","-isystem","C:\\Qt\\Tools\\mingw1120_64\\lib\\gcc\\x86_64-w64-mingw32\\11.2.0\\include\\c++","-isystem","C:\\Qt\\Tools\\mingw1120_64\\lib\\gcc\\x86_64-w64-mingw32\\11.2.0\\include\\c++\\x86_64-w64-mingw32","-isystem","C:\\Qt\\Tools\\mingw1120_64\\lib\\gcc\\x86_64-w64-mingw32\\11.2.0\\include\\c++\\backward","-isystem","C:\\Qt\\Tools\\QtCreator\\bin\\clang\\lib\\clang\\15.0.0\\include","-isystem","C:\\Qt\\Tools\\mingw1120_64\\x86_64-w64-mingw32\\include","-fmessage-length=0","-fdiagnostics-show-note-include-stack","-fretain-comments-from-system-headers","-fmacro-backtrace-limit=0","-ferror-limit=1000","-x","c++","D:\\Repos\\AlgoDemon\\external_src\\camera_module\\src\\autoexposurehandler.cpp"],"directory":"D:/Repos/AlgoDemon/project/build-AlgoDemon-Desktop_Qt_6_4_2_MinGW_64_bit-Debug/.qtc_clangd","file":"D:/Repos/AlgoDemon/external_src/camera_module/src/autoexposurehandler.cpp"},{"arguments":["clang","-Wno-documentation-unknown-command","-Wno-unknown-warning-option","-Wno-unknown-pragmas","-nostdinc","-nostdinc++","-g","-std=gnu++2a","-Wall","-Wextra","-Wextra","-fexceptions","-mthreads","-fsyntax-only","-m64","--target=x86_64-w64-mingw32","-DUNICODE","-D_UNICODE","-DWIN32","-DMINGW_HAS_SECURE_API","-DQT_QML_DEBUG","-DQT_WIDGETS_LIB","-DQT_GUI_LIB","-DQT_CONCURRENT_LIB","-DQT_SERIALPORT_LIB","-DQT_CORE_LIB","-DQT_NEEDS_QMAIN","-DQ_CREATOR_RUN","-IC:\\Qt\\Tools\\QtCreator\\share\\qtcreator\\cplusplus\\wrappedMingwHeaders","-IC:\\Qt\\Tools\\QtCreator\\share\\qtcreator\\cplusplus\\wrappedQtHeaders","-IC:\\Qt\\Tools\\QtCreator\\share\\qtcreator\\cplusplus\\wrappedQtHeaders\\QtCore","-ID:\\Repos\\AlgoDemon\\project\\source","-ID:\\Repos\\AlgoDemon\\external_src","-ID:\\Repos\\AlgoDemon\\external_src\\external\\Qt-Advanced-Docking-System-master\\src","-ID:\\Repos\\AlgoDemon\\external_src\\camera_module\\include","-ID:\\Repos\\AlgoDemon\\external_src\\camera_module\\include\\CameraSDK_include","-IC:\\Qt\\6.4.2\\mingw_64\\include","-IC:\\Qt\\6.4.2\\mingw_64\\include\\QtWidgets","-IC:\\Qt\\6.4.2\\mingw_64\\include\\QtGui","-IC:\\Qt\\6.4.2\\mingw_64\\include\\QtConcurrent","-IC:\\Qt\\6.4.2\\mingw_64\\include\\QtSerialPort","-IC:\\Qt\\6.4.2\\mingw_64\\include\\QtCore","-ID:\\Repos\\AlgoDemon\\project\\build-AlgoDemon-Desktop_Qt_6_4_2_MinGW_64_bit-Debug\\debug","-ID:\\Repos\\AlgoDemon\\project\\build-AlgoDemon-Desktop_Qt_6_4_2_MinGW_64_bit-Debug","-IC:\\Qt\\6.4.2\\mingw_64\\mkspecs\\win32-g++","-isystem","C:\\Qt\\Tools\\mingw1120_64\\lib\\gcc\\x86_64-w64-mingw32\\11.2.0\\include\\c++","-isystem","C:\\Qt\\Tools\\mingw1120_64\\lib\\gcc\\x86_64-w64-mingw32\\11.2.0\\include\\c++\\x86_64-w64-mingw32","-isystem","C:\\Qt\\Tools\\mingw1120_64\\lib\\gcc\\x86_64-w64-mingw32\\11.2.0\\include\\c++\\backward","-isystem","C:\\Qt\\Tools\\QtCreator\\bin\\clang\\lib\\clang\\15.0.0\\include","-isystem","C:\\Qt\\Tools\\mingw1120_64\\x86_64-w64-mingw32\\include","-fmessage-length=0","-fdiagnostics-show-note-include-stack","-fretain-comments-from-system-headers","-fmacro-backtrace-limit=0","-ferror-limit=1000","-x","c++","D:\\Repos\\AlgoDemon\\external_src\\camera_module\\src\\cameraqhyccd.cpp"],"directory":"D:/Repos/AlgoDemon/project/build-AlgoDemon-Desktop_Qt_6_4_2_MinGW_64_bit-Debug/.qtc_clangd","file":"D:/Repos/AlgoDemon/external_src/camera_module/src/cameraqhyccd.cpp"},{"arguments":["clang","-Wno-documentation-unknown-command","-Wno-unknown-warning-option","-Wno-unknown-pragmas","-nostdinc","-nostdinc++","-g","-std=gnu++2a","-Wall","-Wextra","-Wextra","-fexceptions","-mthreads","-fsyntax-only","-m64","--target=x86_64-w64-mingw32","-DUNICODE","-D_UNICODE","-DWIN32","-DMINGW_HAS_SECURE_API","-DQT_QML_DEBUG","-DQT_WIDGETS_LIB","-DQT_GUI_LIB","-DQT_CONCURRENT_LIB","-DQT_SERIALPORT_LIB","-DQT_CORE_LIB","-DQT_NEEDS_QMAIN","-DQ_CREATOR_RUN","-IC:\\Qt\\Tools\\QtCreator\\share\\qtcreator\\cplusplus\\wrappedMingwHeaders","-IC:\\Qt\\Tools\\QtCreator\\share\\qtcreator\\cplusplus\\wrappedQtHeaders","-IC:\\Qt\\Tools\\QtCreator\\share\\qtcreator\\cplusplus\\wrappedQtHeaders\\QtCore","-ID:\\Repos\\AlgoDemon\\project\\source","-ID:\\Repos\\AlgoDemon\\external_src","-ID:\\Repos\\AlgoDemon\\external_src\\external\\Qt-Advanced-Docking-System-master\\src","-ID:\\Repos\\AlgoDemon\\external_src\\camera_module\\include","-ID:\\Repos\\AlgoDemon\\external_src\\camera_module\\include\\CameraSDK_include","-IC:\\Qt\\6.4.2\\mingw_64\\include","-IC:\\Qt\\6.4.2\\mingw_64\\include\\QtWidgets","-IC:\\Qt\\6.4.2\\mingw_64\\include\\QtGui","-IC:\\Qt\\6.4.2\\mingw_64\\include\\QtConcurrent","-IC:\\Qt\\6.4.2\\mingw_64\\include\\QtSerialPort","-IC:\\Qt\\6.4.2\\mingw_64\\include\\QtCore","-ID:\\Repos\\AlgoDemon\\project\\build-AlgoDemon-Desktop_Qt_6_4_2_MinGW_64_bit-Debug\\debug","-ID:\\Repos\\AlgoDemon\\project\\build-AlgoDemon-Desktop_Qt_6_4_2_MinGW_64_bit-Debug","-IC:\\Qt\\6.4.2\\mingw_64\\mkspecs\\win32-g++","-isystem","C:\\Qt\\Tools\\mingw1120_64\\lib\\gcc\\x86_64-w64-mingw32\\11.2.0\\include\\c++","-isystem","C:\\Qt\\Tools\\mingw1120_64\\lib\\gcc\\x86_64-w64-mingw32\\11.2.0\\include\\c++\\x86_64-w64-mingw32","-isystem","C:\\Qt\\Tools\\mingw1120_64\\lib\\gcc\\x86_64-w64-mingw32\\11.2.0\\include\\c++\\backward","-isystem","C:\\Qt\\Tools\\QtCreator\\bin\\clang\\lib\\clang\\15.0.0\\include","-isystem","C:\\Qt\\Tools\\mingw1120_64\\x86_64-w64-mingw32\\include","-fmessage-length=0","-fdiagnostics-show-note-include-stack","-fretain-comments-from-system-headers","-fmacro-backtrace-limit=0","-ferror-limit=1000","-x","c++","D:\\Repos\\AlgoDemon\\external_src\\camera_module\\src\\framepipeline.cpp"],"directory":"D:/Repos/AlgoDemon/project/build-AlgoDemon-Desktop_Qt_6_4_2_MinGW_64_bit-Debug/.qtc_clangd","file":"D:/Repos/AlgoDemon/external_src/camera_module/src/framepipeline.cpp"},{"arguments":["clang","-Wno-documentation-unknown-command","-Wno-unknown-warning-option","-Wno-unknown-pragmas","-nostdinc","-nostdinc++","-g","-std=gnu++2a","-Wall","-Wextra","-Wextra","-fexceptions","-mthreads","-fsyntax-only","-m64","--target=x86_64-w64-mingw32","-DUNICODE","-D_UNICODE","-DWIN32","-DMINGW_HAS_SECURE_API","-DQT_QML_DEBUG","-DQT_WIDGETS_LIB","-DQT_GUI_LIB","-DQT_CONCURRENT_LIB","-DQT_SERIALPORT_LIB","-DQT_CORE_LIB","-DQT_NEEDS_QMAIN","-DQ_CREATOR_RUN","-IC:\\Qt\\Tools\\QtCreator\\share\\qtcreator\\cplusplus\\wrappedMingwHeaders","-IC:\\Qt\\Tools\\QtCreator\\share\\qtcreator\\cplusplus\\wrappedQtHeaders","-IC:\\Qt\\Tools\\QtCreator\\share\\qtcreator\\cplusplus\\wrappedQtHeaders\\QtCore","-ID:\\Repos\\AlgoDemon\\project\\source","-ID:\\Repos\\AlgoDemon\\external_src","-ID:\\Repos\\AlgoDemon\\external_src\\external\\Qt-Advanced-Docking-System-master\\src","-ID:\\Repos\\AlgoDemon\\external_src\\camera_module\\include","-ID:\\Repos\\AlgoDemon\\external_src\\camera_module\\include\\CameraSDK_include","-IC:\\Qt\\6.4.2\\mingw_64\\include","-IC:\\Qt\\6.4.2\\mingw_64\\include\\QtWidgets","-IC:\\Qt\\6.4.2\\mingw_64\\include\\QtGui","-IC:\\Qt\\6.4.2\\mingw_64\\include\\QtConcurrent","-IC:\\Qt\\6.4.2\\mingw_64\\include\\QtSerialPort","-IC:\\Qt\\6.4.2\\mingw_64\\include\\QtCore","-ID:\\Repos\\AlgoDemon\\project\\build-AlgoDemon-Desktop_Qt_6_4_2_MinGW_64_bit-Debug\\debug","-ID:\\Repos\\AlgoDemon\\project\\build-AlgoDemon-Desktop_Qt_6_4_2_MinGW_64_bit-Debug","-IC:\\Qt\\6.4.2\\mingw_64\\mkspecs\\win32-g++","-isystem","C:\\Qt\\Tools\\mingw1120_64\\lib\\gcc\\x86_64-w64-mingw32\\11.2.0\\include\\c++","-isystem","C:\\Qt\\Tools\\mingw1120_64\\lib\\gcc\\x86_64-w64-mingw32\\11.2.0\\include\\c++\\x86_64-w64-mingw32","-isystem","C:\\Qt\\Tools\\mingw1120_64\\lib\\gcc\\x86_64-w64-mingw32\\11.2.0\\include\\c++\\backward","-isystem","C:\\Qt\\Tools\\QtCreator\\bin\\clang\\lib\\clang\\15.0.0\\include","-isystem","C:\\Qt\\Tools\\mingw1120_64\\x86_64-w64-mingw32\\include","-fmessage-length=0","-fdiagnostics-show-note-include-stack","-fretain-comments-from-system-headers","-fmacro-backtrace-limit=0","-ferror-limit=1000","-x","c++","D:\\Repos\\AlgoDemon\\external_src\\camera_module\\src\\imageblurmetric.cpp"],"directory":"D:/Repos/AlgoDemon/project/build-AlgoDemon-Desktop_Qt_6_4_2_MinGW_64_bit-Debug/.qtc_clangd","file":"D:/Repos/AlgoDemon/external_src/camera_module/src/imageblurmetric.cpp"},{"arguments":["clang","-Wno-documentation-unknown-command","-Wno-unknown-warning-option","-Wno-unknown-pragmas","-nostdinc","-nostdinc++","-g","-std=gnu++2a","-Wall","-Wextra","-Wextra","-fexceptions","-mthreads","-fsyntax-only","-m64","--target=x86_64-w64-mingw32","-DUNICODE","-D_UNICODE","-DWIN32","-DMINGW_HAS_SECURE_API","-DQT_QML_DEBUG","-DQT_WIDGETS_LIB","-DQT_GUI_LIB","-DQT_CONCURRENT_LIB","-DQT_SERIALPORT_LIB","-DQT_CORE_LIB","-DQT_NEEDS_QMAIN","-DQ_CREATOR_RUN","-IC:\\Qt\\Tools\\QtCreator\\share\\qtcreator\\cplusplus\\wrappedMingwHeaders","-IC:\\Qt\\Tools\\QtCreator\\share\\qtcreator\\cplusplus\\wrappedQtHeaders","-IC:\\Qt\\Tools\\QtCreator\\share\\qtcreator\\cplusplus\\wrappedQtHeaders\\QtCore","-ID:\\Repos\\AlgoDemon\\project\\source","-ID:\\Repos\\AlgoDemon\\external_src","-ID:\\Repos\\AlgoDemon\\external_src\\external\\Qt-Advanced-Docking-System-master\\src","-ID:\\Repos\\AlgoDemon\\external_src\\camera_module\\include","-ID:\\Repos\\AlgoDemon\\external_src\\camera_module\\include\\CameraSDK_include","-IC:\\Qt\\6.4.2\\mingw_64\\include","-IC:\\Qt\\6.4.2\\mingw_64\\include\\QtWidgets","-IC:\\Qt\\6.4.2\\mingw_64\\include\\QtGui","-IC:\\Qt\\6.4.2\\mingw_64\\include\\QtConcurrent","-IC:\\Qt\\6.4.2\\mingw_64\\include\\QtSerialPort","-IC:\\Qt\\6.4.2\\mingw_64\\include\\QtCore","-ID:\\Repos\\AlgoDemon\\project\\build-AlgoDemon-Desktop_Qt_6_4_2_MinGW_64_bit-Debug\\debug","-ID:\\Repos\\AlgoDemon\\project\\build-AlgoDemon-Desktop_Qt_6_4_2_MinGW_64_bit-Debug","-IC:\\Qt\\6.4.2\\mingw_64\\mkspecs\\win32-g++","-isystem","C:\\Qt\\Tools\\mingw1120_64\\lib\\gcc\\x86_64-w64-mingw32\\11.2.0\\include\\c++","-isystem","C:\\Qt\\Tools\\mingw1120_64\\lib\\gcc\\x86_64-w64-mingw32\\11.2.0\\include\\c++\\x86_64-w64-mingw32","-isystem","C:\\Qt\\Tools\\mingw1120_64\\lib\\gcc\\x86_64-w64-mingw32\\11.2.0\\include\\c++\\backward","-isystem","C:\\Qt\\Tools\\QtCreator\\bin\\clang\\lib\\clang\\15.0.0\\include","-isystem","C:\\Qt\\Tools\\mingw1120_64\\x86_64-w64-mingw32\\include","-fmessage-length=0","-fdiagnostics-show-note-include-stack","-fretain-comments-from-system-headers","-fmacro-backtrace-limit=0","-ferror-limit=1000","-x","c++","D:\\Repos\\AlgoDemon\\external_src\\camera_module\\src\\imageprocess.cpp"],"directory":"D:/Repos/AlgoDemon/project/build-AlgoDemon-Desktop_Qt_6_4_2_MinGW_64_bit-Debug/.qtc_clangd","file":"D:/Repos/AlgoDemon/external_src/camera_module/src/imageprocess.cpp"},{"arguments":["clang","-Wno-documentation-unknown-command","-Wno-unknown-warning-option","-Wno-unknown-pragmas","-nostdinc","-nostdinc++","-g","-std=gnu++2a","-Wall","-Wextra","-Wextra","-fexceptions","-mthreads","-fsyntax-only","-m64","--target=x86_64-w64-mingw32","-DUNICODE","-D_UNICODE","-DWIN32","-DMINGW_HAS_SECURE_API","-DQT_QML_DEBUG","-DQT_WIDGETS_LIB","-DQT_GUI_LIB","-DQT_CONCURRENT_LIB","-DQT_SERIALPORT_LIB","-DQT_CORE_LIB","-DQT_NEEDS_QMAIN","-DQ_CREATOR_RUN","-IC:\\Qt\\Tools\\QtCreator\\share\\qtcreator\\cplusplus\\wrappedMingwHeaders","-IC:\\Qt\\Tools\\QtCreator\\share\\qtcreator\\cplusplus\\wrappedQtHeaders","-IC:\\Qt\\Tools\\QtCreator\\share\\qtcreator\\cplusplus\\wrappedQtHeaders\\QtCore","-ID:\\Repos\\AlgoDemon\\project\\source","-ID:\\Repos\\AlgoDemon\\external_src","-ID:\\Repos\\AlgoDemon\\external_src\\external\\Qt-Advanced-Docking-System-master\\src","-ID:\\Repos\\AlgoDemon\\external_src\\camera_module\\include","-ID:\\Repos\\AlgoDemon\\external_src\\camera_module\\include\\CameraSDK_include","-IC:\\Qt\\6.4.2\\mingw_64\\include","-IC:\\Qt\\6.4.2\\mingw_64\\include\\QtWidgets","-IC:\\Qt\\6.4.2\\mingw_64\\include\\QtGui","-IC:\\Qt\\6.4.2\\mingw_64\\include\\QtConcurrent","-IC:\\Qt\\6.4.2\\mingw_64\\include\\QtSerialPort","-IC:\\Qt\\6.4.2\\mingw_64\\include\\QtCore","-ID:\\Repos\\AlgoDemon\\project\\build-AlgoDemon-Desktop_Qt_6_4_2_MinGW_64_bit-Debug\\debug","-ID:\\Repos\\AlgoDemon\\project\\build-AlgoDemon-Desktop_Qt_6_4_2_MinGW_64_bit-Debug","-IC:\\Qt\\6.4.2\\mingw_64\\mkspecs\\win32-g++","-isystem","C:\\Qt\\Tools\\mingw1120_64\\lib\\gcc\\x86_64-w64-mingw32\\11.2.0\\include\\c++","-isystem","C:\\Qt\\Tools\\mingw1120_64\\lib\\gcc\\x86_64-w64-mingw32\\11.2.0\\include\\c++\\x86_64-w64-mingw32","-isystem","C:\\Qt\\Tools\\mingw1120_64\\lib\\gcc\\x86_64-w64-mingw32\\11.2.0\\include\\c++\\backward","-isystem","C:\\Qt\\Tools\\QtCreator\\bin\\clang\\lib\\clang\\15.0.0\\include","-isystem","C:\\Qt\\Tools\\mingw1120_64\\x86_64-w64-mingw32\\include","-fmessage-length=0","-fdiagnostics-show-note-include-stack","-fretain-comments-from-system-headers","-fmacro-backtrace-limit=0","-ferror-limit=1000","-x","c++","D:\\Repos\\AlgoDemon\\external_src\\camera_module\\src\\objectivecontroller.cpp"],"directory":"D:/Repos/AlgoDemon/project/build-AlgoDemon-Desktop_Qt_6_4_2_MinGW_64_bit-Debug/.qtc_clangd","file":"D:/Repos/AlgoDemon/external_src/camera_module/src/objectivecontroller.cpp"},{"arguments":["clang","-Wno-documentation-unknown-command","-Wno-unknown-warning-option","-Wno-unknown-pragmas","-nostdinc","-nostdinc++","-g","-std=gnu++2a","-Wall","-Wextra","-Wextra","-fexceptions","-mthreads","-fsyntax-only","-m64","--target=x86_64-w64-mingw32","-DUNICODE","-D_UNICODE","-DWIN32","-DMINGW_HAS_SECURE_API","-DQT_QML_DEBUG","-DQT_WIDGETS_LIB","-DQT_GUI_LIB","-DQT_CONCURRENT_LIB","-DQT_SERIALPORT_LIB","-DQT_CORE_LIB","-DQT_NEEDS_QMAIN","-DQ_CREATOR_RUN","-IC:\\Qt\\Tools\\QtCreator\\share\\qtcreator\\cplusplus\\wrappedMingwHeaders","-IC:\\Qt\\Tools\\QtCreator\\share\\qtcreator\\cplusplus\\wrappedQtHeaders","-IC:\\Qt\\Tools\\QtCreator\\share\\qtcreator\\cplusplus\\wrappedQtHeaders\\QtCore","-ID:\\Repos\\AlgoDemon\\project\\source","-ID:\\Repos\\AlgoDemon\\external_src","-ID:\\Repos\\AlgoDemon\\external_src\\external\\Qt-Advanced-Docking-System-master\\src","-ID:\\Repos\\AlgoDemon\\external_src\\camera_module\\include","-ID:\\Repos\\AlgoDemon\\external_src\\camera_module\\include\\CameraSDK_include","-IC:\\Qt\\6.4.2\\mingw_64\\include","-IC:\\Qt\\6.4.2\\mingw_64\\include\\QtWidgets","-IC:\\Qt\\6.4.2\\mingw_64\\include\\QtGui","-IC:\\Qt\\6.4.2\\mingw_64\\include\\QtConcurrent","-IC:\\Qt\\6.4.2\\mingw_64\\include\\QtSerialPort","-IC:\\Qt\\6.4.2\\mingw_64\\include\\QtCore","-ID:\\Repos\\AlgoDemon\\project\\build-AlgoDemon-Desktop_Qt_6_4_2_MinGW_64_bit-Debug\\debug","-ID:\\Repos\\AlgoDemon\\project\\build-AlgoDemon-Desktop_Qt_6_4_2_MinGW_64_bit-Debug","-IC:\\Qt\\6.4.2\\mingw_64\\mkspecs\\win32-g++","-isystem","C:\\Qt\\Tools\\mingw1120_64\\lib\\gcc\\x86_64-w64-mingw32\\11.2.0\\include\\c++","-isystem","C:\\Qt\\Tools\\mingw1120_64\\lib\\gcc\\x86_64-w64-mingw32\\11.2.0\\include\\c++\\x86_64-w64-mingw32","-isystem","C:\\Qt\\Tools\\mingw1120_64\\lib\\gcc\\x86_64-w64-mingw32\\11.2.0\\include\\c++\\backward","-isystem","C:\\Qt\\Tools\\QtCreator\\bin\\clang\\lib\\clang\\15.0.0\\include","-isystem","C:\\Qt\\Tools\\mingw1120_64\\x86_64-w64-mingw32\\include","-fmessage-length=0","-fdiagnostics-show-note-include-stack","-fretain-comments-from-system-headers","-fmacro-backtrace-limit=0","-ferror-limit=1000","-x","c++","D:\\Repos\\AlgoDemon\\external_src\\camera_module\\src\\serialib.cpp"],"directory":"D:/Repos/AlgoDemon/project/build-AlgoDemon-Desktop_Qt_6_4_2_MinGW_64_bit-Debug/.qtc_clangd","file":"D:/Repos/AlgoDemon/external_src/camera_module/src/serialib.cpp"},{"arguments":["clang","-Wno-documentation-unknown-command","-Wno-unknown-warning-option","-Wno-unknown-pragmas","-nostdinc","-nostdinc++","-g","-std=gnu++2a","-Wall","-Wextra","-Wextra","-fexceptions","-mthreads","-fsyntax-only","-m64","--target=x86_64-w64-mingw32","-DUNICODE","-D_UNICODE","-DWIN32","-DMINGW_HAS_SECURE_API","-DQT_QML_DEBUG","-DQT_WIDGETS_LIB","-DQT_GUI_LIB","-DQT_CONCURRENT_LIB","-DQT_SERIALPORT_LIB","-DQT_CORE_LIB","-DQT_NEEDS_QMAIN","-DQ_CREATOR_RUN","-IC:\\Qt\\Tools\\QtCreator\\share\\qtcreator\\cplusplus\\wrappedMingwHeaders","-IC:\\Qt\\Tools\\QtCreator\\share\\qtcreator\\cplusplus\\wrappedQtHeaders","-IC:\\Qt\\Tools\\QtCreator\\share\\qtcreator\\cplusplus\\wrappedQtHeaders\\QtCore","-ID:\\Repos\\AlgoDemon\\project\\source","-ID:\\Repos\\AlgoDemon\\external_src","-ID:\\Repos\\AlgoDemon\\external_src\\external\\Qt-Advanced-Docking-System-master\\src","-ID:\\Repos\\AlgoDemon\\external_src\\camera_module\\include","-ID:\\Repos\\AlgoDemon\\external_src\\camera_module\\include\\CameraSDK_include","-IC:\\Qt\\6.4.2\\mingw_64\\include","-IC:\\Qt\\6.4.2\\mingw_64\\include\\QtWidgets","-IC:\\Qt\\6.4.2\\mingw_64\\include\\QtGui","-IC:\\Qt\\6.4.2\\mingw_64\\include\\QtConcurrent","-IC:\\Qt\\6.4.2\\mingw_64\\include\\QtSerialPort","-IC:\\Qt\\6.4.2\\mingw_64\\include\\QtCore","-ID:\\Repos\\AlgoDemon\\project\\build-AlgoDemon-Desktop_Qt_6_4_2_MinGW_64_bit-Debug\\debug","-ID:\\Repos\\AlgoDemon\\project\\build-AlgoDemon-Desktop_Qt_6_4_2_MinGW_64_bit-Debug","-IC:\\Qt\\6.4.2\\mingw_64\\mkspecs\\win32-g++","-isystem","C:\\Qt\\Tools\\mingw1120_64\\lib\\gcc\\x86_64-w64-mingw32\\11.2.0\\include\\c++","-isystem","C:\\Qt\\Tools\\mingw1120_64\\lib\\gcc\\x86_64-w64-mingw32\\11.2.0\\include\\c++\\x86_64-w64-mingw32","-isystem","C:\\Qt\\Tools\\mingw1120_64\\lib\\gcc\\x86_64-w64-mingw32\\11.2.0\\include\\c++\\backward","-isystem","C:\\Qt\\Tools\\QtCreator\\bin\\clang\\lib\\clang\\15.0.0\\include","-isystem","C:\\Qt\\Tools\\mingw1120_64\\x86_64-w64-mingw32\\include","-fmessage-length=0","-fdiagnostics-show-note-include-stack","-fretain-comments-from-system-headers","-fmacro-backtrace-limit=0","-ferror-limit=1000","-x","c++-header","D:\\Repos\\AlgoDemon\\project\\source\\appprocessor.h"],"directory":"D:/Repos/AlgoDemon/project/build-AlgoDemon-Desktop_Qt_6_4_2_MinGW_64_bit-Debug/.qtc_clangd","file":"D:/Repos/AlgoDemon/project/source/appprocessor.h"},{"arguments":["clang","-Wno-documentation-unknown-command","-Wno-unknown-warning-option","-Wno-unknown-pragmas","-nostdinc","-nostdinc++","-g","-std=gnu++2a","-Wall","-Wextra","-Wextra","-fexceptions","-mthreads","-fsyntax-only","-m64","--target=x86_64-w64-mingw32","-DUNICODE","-D_UNICODE","-DWIN32","-DMINGW_HAS_SECURE_API","-DQT_QML_DEBUG","-DQT_WIDGETS_LIB","-DQT_GUI_LIB","-DQT_CONCURRENT_LIB","-DQT_SERIALPORT_LIB","-DQT_CORE_LIB","-DQT_NEEDS_QMAIN","-DQ_CREATOR_RUN","-IC:\\Qt\\Tools\\QtCreator\\share\\qtcreator\\cplusplus\\wrappedMingwHeaders","-IC:\\Qt\\Tools\\QtCreator\\share\\qtcreator\\cplusplus\\wrappedQtHeaders","-IC:\\Qt\\Tools\\QtCreator\\share\\qtcreator\\cplusplus\\wrappedQtHeaders\\QtCore","-ID:\\Repos\\AlgoDemon\\project\\source","-ID:\\Repos\\AlgoDemon\\external_src","-ID:\\Repos\\AlgoDemon\\external_src\\external\\Qt-Advanced-Docking-System-master\\src","-ID:\\Repos\\AlgoDemon\\external_src\\camera_module\\include","-ID:\\Repos\\AlgoDemon\\external_src\\camera_module\\include\\CameraSDK_include","-IC:\\Qt\\6.4.2\\mingw_64\\include","-IC:\\Qt\\6.4.2\\mingw_64\\include\\QtWidgets","-IC:\\Qt\\6.4.2\\mingw_64\\include\\QtGui","-IC:\\Qt\\6.4.2\\mingw_64\\include\\QtConcurrent","-IC:\\Qt\\6.4.2\\mingw_64\\include\\QtSerialPort","-IC:\\Qt\\6.4.2\\mingw_64\\include\\QtCore","-ID:\\Repos\\AlgoDemon\\project\\build-AlgoDemon-Desktop_Qt_6_4_2_MinGW_64_bit-Debug\\debug","-ID:\\Repos\\AlgoDemon\\project\\build-AlgoDemon-Desktop_Qt_6_4_2_MinGW_64_bit-Debug","-IC:\\Qt\\6.4.2\\mingw_64\\mkspecs\\win32-g++","-isystem","C:\\Qt\\Tools\\mingw1120_64\\lib\\gcc\\x86_64-w64-mingw32\\11.2.0\\include\\c++","-isystem","C:\\Qt\\Tools\\mingw1120_64\\lib\\gcc\\x86_64-w64-mingw32\\11.2.0\\include\\c++\\x86_64-w64-mingw32","-isystem","C:\\Qt\\Tools\\mingw1120_64\\lib\\gcc\\x86_64-w64-mingw32\\11.2.0\\include\\c++\\backward","-isystem","C:\\Qt\\Tools\\QtCreator\\bin\\clang\\lib\\clang\\15.0.0\\include","-isystem","C:\\Qt\\Tools\\mingw1120_64\\x86_64-w64-mingw32\\include","-fmessage-length=0","-fdiagnostics-show-note-include-stack","-fretain-comments-from-system-headers","-fmacro-backtrace-limit=0","-ferror-limit=1000","-x","c++-header","D:\\Repos\\AlgoDemon\\project\\source\\camerathread.h"],"directory":"D:/Repos/AlgoDemon/project/build-AlgoDemon-Desktop_Qt_6_4_2_MinGW_64_bit-Debug/.qtc_clangd","file":"D:/Repos/AlgoDemon/project/source/camerathread.h"},{"arguments":["clang","-Wno-documentation-unknown-command","-Wno-unknown-warning-option","-Wno-unknown-pragmas","-nostdinc","-nostdinc++","-g","-std=gnu++2a","-Wall","-Wextra","-Wextra","-fexceptions","-mthreads","-fsyntax-only","-m64","--target=x86_64-w64-mingw32","-DUNICODE","-D_UNICODE","-DWIN32","-DMINGW_HAS_SECURE_API","-DQT_QML_DEBUG","-DQT_WIDGETS_LIB","-DQT_GUI_LIB","-DQT_CONCURRENT_LIB","-DQT_SERIALPORT_LIB","-DQT_CORE_LIB","-DQT_NEEDS_QMAIN","-DQ_CREATOR_RUN","-IC:\\Qt\\Tools\\QtCreator\\share\\qtcreator\\cplusplus\\wrappedMingwHeaders","-IC:\\Qt\\Tools\\QtCreator\\share\\qtcreator\\cplusplus\\wrappedQtHeaders","-IC:\\Qt\\Tools\\QtCreator\\share\\qtcreator\\cplusplus\\wrappedQtHeaders\\QtCore","-ID:\\Repos\\AlgoDemon\\project\\source","-ID:\\Repos\\AlgoDemon\\external_src","-ID:\\Repos\\AlgoDemon\\external_src\\external\\Qt-Advanced-Docking-System-master\\src","-ID:\\Repos\\AlgoDemon\\external_src\\camera_module\\include","-ID:\\Repos\\AlgoDemon\\external_src\\camera_module\\include\\CameraSDK_include","-IC:\\Qt\\6.4.2\\mingw_64\\include","-IC:\\Qt\\6.4.2\\mingw_64\\include\\QtWidgets","-IC:\\Qt\\6.4.2\\mingw_64\\include\\QtGui","-IC:\\Qt\\6.4.2\\mingw_64\\include\\QtConcurrent","-IC:\\Qt\\6.4.2\\mingw_64\\include\\QtSerialPort","-IC:\\Qt\\6.4.2\\mingw_64\\include\\QtCore","-ID:\\Repos\\AlgoDemon\\project\\build-AlgoDemon-Desktop_Qt_6_4_2_MinGW_64_bit-Debug\\debug","-ID:\\Repos\\AlgoDemon\\project\\build-AlgoDemon-Desktop_Qt_6_4_2_MinGW_64_bit-Debug","-IC:\\Qt\\6.4.2\\mingw_64\\mkspecs\\win32-g++","-isystem","C:\\Qt\\Tools\\mingw1120_64\\lib\\gcc\\x86_64-w64-mingw32\\11.2.0\\include\\c++","-isystem","C:\\Qt\\Tools\\mingw1120_64\\lib\\gcc\\x86_64-w64-mingw32\\11.2.0\\include\\c++\\x86_64-w64-mingw32","-isystem","C:\\Qt\\Tools\\mingw1120_64\\lib\\gcc\\x86_64-w64-mingw32\\11.2.0\\include\\c++\\backward","-isystem","C:\\Qt\\Tools\\QtCreator\\bin\\clang\\lib\\clang\\15.0.0\\include","-isystem","C:\\Qt\\Tools\\mingw1120_64\\x86_64-w64-mingw32\\include","-fmessage-length=0","-fdiagnostics-show-note-include-stack","-fretain-comments-from-system-headers","-fmacro-backtrace-limit=0","-ferror-limit=1000","-x","c++-header","D:\\Repos\\AlgoDemon\\project\\source\\mainwindow.h"],"directory":"D:/Repos/AlgoDemon/project/build-AlgoDemon-Desktop_Qt_6_4_2_MinGW_64_bit-Debug/.qtc_clangd","file":"D:/Repos/AlgoDemon/project/source/mainwindow.h"},{"arguments":["clang","-Wno-documentation-unknown-command","-Wno-unknown-warning-option","-Wno-unknown-pragmas","-nostdinc","-nostdinc++","-g","-std=gnu++2a","-Wall","-Wextra","-Wextra","-fexceptions","-mthreads","-fsyntax-only","-m64","--target=x86_64-w64-mingw32","-DUNICODE","-D_UNICODE","-DWIN32","-DMINGW_HAS_SECURE_API","-DQT_QML_DEBUG","-DQT_WIDGETS_LIB","-DQT_GUI_LIB","-DQT_CONCURRENT_LIB","-DQT_SERIALPORT_LIB","-DQT_CORE_LIB","-DQT_NEEDS_QMAIN","-DQ_CREATOR_RUN","-IC:\\Qt\\Tools\\QtCreator\\share\\qtcreator\\cplusplus\\wrappedMingwHeaders","-IC:\\Qt\\Tools\\QtCreator\\share\\qtcreator\\cplusplus\\wrappedQtHeaders","-IC:\\Qt\\Tools\\QtCreator\\share\\qtcreator\\cplusplus\\wrappedQtHeaders\\QtCore","-ID:\\Repos\\AlgoDemon\\project\\source","-ID:\\Repos\\AlgoDemon\\external_src","-ID:\\Repos\\AlgoDemon\\external_src\\external\\Qt-Advanced-Docking-System-master\\src","-ID:\\Repos\\AlgoDemon\\external_src\\camera_module\\include","-ID:\\Repos\\AlgoDemon\\external_src\\camera_module\\include\\CameraSDK_include","-IC:\\Qt\\6.4.2\\mingw_64\\include","-IC:\\Qt\\6.4.2\\mingw_64\\include\\QtWidgets","-IC:\\Qt\\6.4.2\\mingw_64\\include\\QtGui","-IC:\\Qt\\6.4.2\\mingw_64\\include\\QtConcurrent","-IC:\\Qt\\6.4.2\\mingw_64\\include\\QtSerialPort","-IC:\\Qt\\6.4.2\\mingw_64\\include\\QtCore","-ID:\\Repos\\AlgoDemon\\project\\build-AlgoDemon-Desktop_Qt_6_4_2_MinGW_64_bit-Debug\\debug","-ID:\\Repos\\AlgoDemon\\project\\build-AlgoDemon-Desktop_Qt_6_4_2_MinGW_64_bit-Debug","-IC:\\Qt\\6.4.2\\mingw_64\\mkspecs\\win32-g++","-isystem","C:\\Qt\\Tools\\mingw1120_64\\lib\\gcc\\x86_64-w64-mingw32\\11.2.0\\include\\c++","-isystem","C:\\Qt\\Tools\\mingw1120_64\\lib\\gcc\\x86_64-w64-mingw32\\11.2.0\\include\\c++\\x86_64-w64-mingw32","-isystem","C:\\Qt\\Tools\\mingw1120_64\\lib\\gcc\\x86_64-w64-mingw32\\11.2.0\\include\\c++\\backward","-isystem","C:\\Qt\\Tools\\QtCreator\\bin\\clang\\lib\\clang\\15.0.0\\include","-isystem","C:\\Qt\\Tools\\mingw1120_64\\x86_64-w64-mingw32\\include","-fmessage-length=0","-fdiagnostics-show-note-include-stack","-fretain-comments-from-system-headers","-fmacro-backtrace-limit=0","-ferror-limit=1000","-x","c++-header","D:\\Repos\\AlgoDemon\\project\\source\\mattoqimage.h"],"directory":"D:/Repos/AlgoDemon/project/build-AlgoDemon-Desktop_Qt_6_4_2_MinGW_64_bit-Debug/.qtc_clangd","file":"D:/Repos/AlgoDemon/project/source/mattoqimage.h"},{"arguments":["clang","-Wno-documentation-unknown-command","-Wno-unknown-warning-option","-Wno-unknown-pragmas","-nostdinc","-nostdinc++","-g","-std=gnu++2a","-Wall","-Wextra","-Wextra","-fexceptions","-mthreads","-fsyntax-only","-m64","--target=x86_64-w64-mingw32","-DUNICODE","-D_UNICODE","-DWIN32","-DMINGW_HAS_SECURE_API","-DQT_QML_DEBUG","-DQT_WIDGETS_LIB","-DQT_GUI_LIB","-DQT_CONCURRENT_LIB","-DQT_SERIALPORT_LIB","-DQT_CORE_LIB","-DQT_NEEDS_QMAIN","-DQ_CREATOR_RUN","-IC:\\Qt\\Tools\\QtCreator\\share\\qtcreator\\cplusplus\\wrappedMingwHeaders","-IC:\\Qt\\Tools\\QtCreator\\share\\qtcreator\\cplusplus\\wrappedQtHeaders","-IC:\\Qt\\Tools\\QtCreator\\share\\qtcreator\\cplusplus\\wrappedQtHeaders\\QtCore","-ID:\\Repos\\AlgoDemon\\project\\source","-ID:\\Repos\\AlgoDemon\\external_src","-ID:\\Repos\\AlgoDemon\\external_src\\external\\Qt-Advanced-Docking-System-master\\src","-ID:\\Repos\\AlgoDemon\\external_src\\camera_module\\include","-ID:\\Repos\\AlgoDemon\\external_src\\camera_module\\include\\CameraSDK_include","-IC:\\Qt\\6.4.2\\mingw_64\\include","-IC:\\Qt\\6.4.2\\mingw_64\\include\\QtWidgets","-IC:\\Qt\\6.4.2\\mingw_64\\include\\QtGui","-IC:\\Qt\\6.4.2\\mingw_64\\include\\QtConcurrent","-IC:\\Qt\\6.4.2\\mingw_64\\include\\QtSerialPort","-IC:\\Qt\\6.4.2\\mingw_64\\include\\QtCore","-ID:\\Repos\\AlgoDemon\\project\\build-AlgoDemon-Desktop_Qt_6_4_2_MinGW_64_bit-Debug\\debug","-ID:\\Repos\\AlgoDemon\\project\\build-AlgoDemon-Desktop_Qt_6_4_2_MinGW_64_bit-Debug","-IC:\\Qt\\6.4.2\\mingw_64\\mkspecs\\win32-g++","-isystem","C:\\Qt\\Tools\\mingw1120_64\\lib\\gcc\\x86_64-w64-mingw32\\11.2.0\\include\\c++","-isystem","C:\\Qt\\Tools\\mingw1120_64\\lib\\gcc\\x86_64-w64-mingw32\\11.2.0\\include\\c++\\x86_64-w64-mingw32","-isystem","C:\\Qt\\Tools\\mingw1120_64\\lib\\gcc\\x86_64-w64-mingw32\\11.2.0\\include\\c++\\backward","-isystem","C:\\Qt\\Tools\\QtCreator\\bin\\clang\\lib\\clang\\15.0.0\\include","-isystem","C:\\Qt\\Tools\\mingw1120_64\\x86_64-w64-mingw32\\include","-fmessage-length=0","-fdiagnostics-show-note-include-stack","-fretain-comments-from-system-headers","-fmacro-backtrace-limit=0","-ferror-limit=1000","-x","c++-header","D:\\Repos\\AlgoDemon\\project\\source\\objectivethread.h"],"directory":"D:/Repos/AlgoDemon/project/build-AlgoDemon-Desktop_Qt_6_4_2_MinGW_64_bit-Debug/.qtc_clangd","file":"D:/Repos/AlgoDemon/project/source/objectivethread.h"},{"arguments":["clang","-Wno-documentation-unknown-command","-Wno-unknown-warning-option","-Wno-unknown-pragmas","-nostdinc","-nostdinc++","-g","-std=gnu++2a","-Wall","-Wextra","-Wextra","-fexceptions","-mthreads","-fsyntax-only","-m64","--target=x86_64-w64-mingw32","-DUNICODE","-D_UNICODE","-DWIN32","-DMINGW_HAS_SECURE_API","-DQT_QML_DEBUG","-DQT_WIDGETS_LIB","-DQT_GUI_LIB","-DQT_CONCURRENT_LIB","-DQT_SERIALPORT_LIB","-DQT_CORE_LIB","-DQT_NEEDS_QMAIN","-DQ_CREATOR_RUN","-IC:\\Qt\\Tools\\QtCreator\\share\\qtcreator\\cplusplus\\wrappedMingwHeaders","-IC:\\Qt\\Tools\\QtCreator\\share\\qtcreator\\cplusplus\\wrappedQtHeaders","-IC:\\Qt\\Tools\\QtCreator\\share\\qtcreator\\cplusplus\\wrappedQtHeaders\\QtCore","-ID:\\Repos\\AlgoDemon\\project\\source","-ID:\\Repos\\AlgoDemon\\external_src","-ID:\\Repos\\AlgoDemon\\external_src\\external\\Qt-Advanced-Docking-System-master\\src","-ID:\\Repos\\AlgoDemon\\external_src\\camera_module\\include","-ID:\\Repos\\AlgoDemon\\external_src\\camera_module\\include\\CameraSDK_include","-IC:\\Qt\\6.4.2\\mingw_64\\include","-IC:\\Qt\\6.4.2\\mingw_64\\include\\QtWidgets","-IC:\\Qt\\6.4.2\\mingw_64\\include\\QtGui","-IC:\\Qt\\6.4.2\\mingw_64\\include\\QtConcurrent","-IC:\\Qt\\6.4.2\\mingw_64\\include\\QtSerialPort","-IC:\\Qt\\6.4.2\\mingw_64\\include\\QtCore","-ID:\\Repos\\AlgoDemon\\project\\build-AlgoDemon-Desktop_Qt_6_4_2_MinGW_64_bit-Debug\\debug","-ID:\\Repos\\AlgoDemon\\project\\build-AlgoDemon-Desktop_Qt_6_4_2_MinGW_64_bit-Debug","-IC:\\Qt\\6.4.2\\mingw_64\\mkspecs\\win32-g++","-isystem","C:\\Qt\\Tools\\mingw1120_64\\lib\\gcc\\x86_64-w64-mingw32\\11.2.0\\include\\c++","-isystem","C:\\Qt\\Tools\\mingw1120_64\\lib\\gcc\\x86_64-w64-mingw32\\11.2.0\\include\\c++\\x86_64-w64-mingw32","-isystem","C:\\Qt\\Tools\\mingw1120_64\\lib\\gcc\\x86_64-w64-mingw32\\11.2.0\\include\\c++\\backward","-isystem","C:\\Qt\\Tools\\QtCreator\\bin\\clang\\lib\\clang\\15.0.0\\include","-isystem","C:\\Qt\\Tools\\mingw1120_64\\x86_64-w64-mingw32\\include","-fmessage-length=0","-fdiagnostics-show-note-include-stack","-fretain-comments-from-system-headers","-fmacro-backtrace-limit=0","-ferror-limit=1000","-x","c++-header","D:\\Repos\\AlgoDemon\\project\\source\\processingthread.h"],"directory":"D:/Repos/AlgoDemon/project/build-AlgoDemon-Desktop_Qt_6_4_2_MinGW_64_bit-Debug/.qtc_clangd","file":"D:/Repos/AlgoDemon/project/source/processingthread.h"},{"arguments":["clang","-Wno-documentation-unknown-command","-Wno-unknown-warning-option","-Wno-unknown-pragmas","-nostdinc","-nostdinc++","-g","-std=gnu++2a","-Wall","-Wextra","-Wextra","-fexceptions","-mthreads","-fsyntax-only","-m64","--target=x86_64-w64-mingw32","-DUNICODE","-D_UNICODE","-DWIN32","-DMINGW_HAS_SECURE_API","-DQT_QML_DEBUG","-DQT_WIDGETS_LIB","-DQT_GUI_LIB","-DQT_CONCURRENT_LIB","-DQT_SERIALPORT_LIB","-DQT_CORE_LIB","-DQT_NEEDS_QMAIN","-DQ_CREATOR_RUN","-IC:\\Qt\\Tools\\QtCreator\\share\\qtcreator\\cplusplus\\wrappedMingwHeaders","-IC:\\Qt\\Tools\\QtCreator\\share\\qtcreator\\cplusplus\\wrappedQtHeaders","-IC:\\Qt\\Tools\\QtCreator\\share\\qtcreator\\cplusplus\\wrappedQtHeaders\\QtCore","-ID:\\Repos\\AlgoDemon\\project\\source","-ID:\\Repos\\AlgoDemon\\external_src","-ID:\\Repos\\AlgoDemon\\external_src\\external\\Qt-Advanced-Docking-System-master\\src","-ID:\\Repos\\AlgoDemon\\external_src\\camera_module\\include","-ID:\\Repos\\AlgoDemon\\external_src\\camera_module\\include\\CameraSDK_include","-IC:\\Qt\\6.4.2\\mingw_64\\include","-IC:\\Qt\\6.4.2\\mingw_64\\include\\QtWidgets","-IC:\\Qt\\6.4.2\\mingw_64\\include\\QtGui","-IC:\\Qt\\6.4.2\\mingw_64\\include\\QtConcurrent","-IC:\\Qt\\6.4.2\\mingw_64\\include\\QtSerialPort","-IC:\\Qt\\6.4.2\\mingw_64\\include\\QtCore","-ID:\\Repos\\AlgoDemon\\project\\build-AlgoDemon-Desktop_Qt_6_4_2_MinGW_64_bit-Debug\\debug","-ID:\\Repos\\AlgoDemon\\project\\build-AlgoDemon-Desktop_Qt_6_4_2_MinGW_64_bit-Debug","-IC:\\Qt\\6.4.2\\mingw_64\\mkspecs\\win32-g++","-isystem","C:\\Qt\\Tools\\mingw1120_64\\lib\\gcc\\x86_64-w64-mingw32\\11.2.0\\include\\c++","-isystem","C:\\Qt\\Tools\\mingw1120_64\\lib\\gcc\\x86_64-w64-mingw32\\11.2.0\\include\\c++\\x86_64-w64-mingw32","-isystem","C:\\Qt\\Tools\\mingw1120_64\\lib\\gcc\\x86_64-w64-mingw32\\11.2.0\\include\\c++\\backward","-isystem","C:\\Qt\\Tools\\QtCreator\\bin\\clang\\lib\\clang\\15.0.0\\include","-isystem","C:\\Qt\\Tools\\mingw1120_64\\x86_64-w64-mingw32\\include","-fmessage-length=0","-fdiagnostics-show-note-include-stack","-fretain-comments-from-system-headers","-fmacro-backtrace-limit=0","-ferror-limit=1000","-x","c++-header","D:\\Repos\\AlgoDemon\\project\\source\\structures.h"],"directory":"D:/Repos/AlgoDemon/project/build-AlgoDemon-Desktop_Qt_6_4_2_MinGW_64_bit-Debug/.qtc_clangd","file":"D:/Repos/AlgoDemon/project/source/structures.h"},{"arguments":["clang","-Wno-documentation-unknown-command","-Wno-unknown-warning-option","-Wno-unknown-pragmas","-nostdinc","-nostdinc++","-g","-std=gnu++2a","-Wall","-Wextra","-Wextra","-fexceptions","-mthreads","-fsyntax-only","-m64","--target=x86_64-w64-mingw32","-DUNICODE","-D_UNICODE","-DWIN32","-DMINGW_HAS_SECURE_API","-DQT_QML_DEBUG","-DQT_WIDGETS_LIB","-DQT_GUI_LIB","-DQT_CONCURRENT_LIB","-DQT_SERIALPORT_LIB","-DQT_CORE_LIB","-DQT_NEEDS_QMAIN","-DQ_CREATOR_RUN","-IC:\\Qt\\Tools\\QtCreator\\share\\qtcreator\\cplusplus\\wrappedMingwHeaders","-IC:\\Qt\\Tools\\QtCreator\\share\\qtcreator\\cplusplus\\wrappedQtHeaders","-IC:\\Qt\\Tools\\QtCreator\\share\\qtcreator\\cplusplus\\wrappedQtHeaders\\QtCore","-ID:\\Repos\\AlgoDemon\\project\\source","-ID:\\Repos\\AlgoDemon\\external_src","-ID:\\Repos\\AlgoDemon\\external_src\\external\\Qt-Advanced-Docking-System-master\\src","-ID:\\Repos\\AlgoDemon\\external_src\\camera_module\\include","-ID:\\Repos\\AlgoDemon\\external_src\\camera_module\\include\\CameraSDK_include","-IC:\\Qt\\6.4.2\\mingw_64\\include","-IC:\\Qt\\6.4.2\\mingw_64\\include\\QtWidgets","-IC:\\Qt\\6.4.2\\mingw_64\\include\\QtGui","-IC:\\Qt\\6.4.2\\mingw_64\\include\\QtConcurrent","-IC:\\Qt\\6.4.2\\mingw_64\\include\\QtSerialPort","-IC:\\Qt\\6.4.2\\mingw_64\\include\\QtCore","-ID:\\Repos\\AlgoDemon\\project\\build-AlgoDemon-Desktop_Qt_6_4_2_MinGW_64_bit-Debug\\debug","-ID:\\Repos\\AlgoDemon\\project\\build-AlgoDemon-Desktop_Qt_6_4_2_MinGW_64_bit-Debug","-IC:\\Qt\\6.4.2\\mingw_64\\mkspecs\\win32-g++","-isystem","C:\\Qt\\Tools\\mingw1120_64\\lib\\gcc\\x86_64-w64-mingw32\\11.2.0\\include\\c++","-isystem","C:\\Qt\\Tools\\mingw1120_64\\lib\\gcc\\x86_64-w64-mingw32\\11.2.0\\include\\c++\\x86_64-w64-mingw32","-isystem","C:\\Qt\\Tools\\mingw1120_64\\lib\\gcc\\x86_64-w64-mingw32\\11.2.0\\include\\c++\\backward","-isystem","C:\\Qt\\Tools\\QtCreator\\bin\\clang\\lib\\clang\\15.0.0\\include","-isystem","C:\\Qt\\Tools\\mingw1120_64\\x86_64-w64-mingw32\\include","-fmessage-length=0","-fdiagnostics-show-note-include-stack","-fretain-comments-from-system-headers","-fmacro-backtrace-limit=0","-ferror-limit=1000","-x","c++-header","D:\\Repos\\AlgoDemon\\external_src\\widgets\\graphicsview.h"],"directory":"D:/Repos/AlgoDemon/project/build-AlgoDemon-Desktop_Qt_6_4_2_MinGW_64_bit-Debug/.qtc_clangd","file":"D:/Repos/AlgoDemon/external_src/widgets/graphicsview.h"},{"arguments":["clang","-Wno-documentation-unknown-command","-Wno-unknown-warning-option","-Wno-unknown-pragmas","-nostdinc","-nostdinc++","-g","-std=gnu++2a","-Wall","-Wextra","-Wextra","-fexceptions","-mthreads","-fsyntax-only","-m64","--target=x86_64-w64-mingw32","-DUNICODE","-D_UNICODE","-DWIN32","-DMINGW_HAS_SECURE_API","-DQT_QML_DEBUG","-DQT_WIDGETS_LIB","-DQT_GUI_LIB","-DQT_CONCURRENT_LIB","-DQT_SERIALPORT_LIB","-DQT_CORE_LIB","-DQT_NEEDS_QMAIN","-DQ_CREATOR_RUN","-IC:\\Qt\\Tools\\QtCreator\\share\\qtcreator\\cplusplus\\wrappedMingwHeaders","-IC:\\Qt\\Tools\\QtCreator\\share\\qtcreator\\cplusplus\\wrappedQtHeaders","-IC:\\Qt\\Tools\\QtCreator\\share\\qtcreator\\cplusplus\\wrappedQtHeaders\\QtCore","-ID:\\Repos\\AlgoDemon\\project\\source","-ID:\\Repos\\AlgoDemon\\external_src","-ID:\\Repos\\AlgoDemon\\external_src\\external\\Qt-Advanced-Docking-System-master\\src","-ID:\\Repos\\AlgoDemon\\external_src\\camera_module\\include","-ID:\\Repos\\AlgoDemon\\external_src\\camera_module\\include\\CameraSDK_include","-IC:\\Qt\\6.4.2\\mingw_64\\include","-IC:\\Qt\\6.4.2\\mingw_64\\include\\QtWidgets","-IC:\\Qt\\6.4.2\\mingw_64\\include\\QtGui","-IC:\\Qt\\6.4.2\\mingw_64\\include\\QtConcurrent","-IC:\\Qt\\6.4.2\\mingw_64\\include\\QtSerialPort","-IC:\\Qt\\6.4.2\\mingw_64\\include\\QtCore","-ID:\\Repos\\AlgoDemon\\project\\build-AlgoDemon-Desktop_Qt_6_4_2_MinGW_64_bit-Debug\\debug","-ID:\\Repos\\AlgoDemon\\project\\build-AlgoDemon-Desktop_Qt_6_4_2_MinGW_64_bit-Debug","-IC:\\Qt\\6.4.2\\mingw_64\\mkspecs\\win32-g++","-isystem","C:\\Qt\\Tools\\mingw1120_64\\lib\\gcc\\x86_64-w64-mingw32\\11.2.0\\include\\c++","-isystem","C:\\Qt\\Tools\\mingw1120_64\\lib\\gcc\\x86_64-w64-mingw32\\11.2.0\\include\\c++\\x86_64-w64-mingw32","-isystem","C:\\Qt\\Tools\\mingw1120_64\\lib\\gcc\\x86_64-w64-mingw32\\11.2.0\\include\\c++\\backward","-isystem","C:\\Qt\\Tools\\QtCreator\\bin\\clang\\lib\\clang\\15.0.0\\include","-isystem","C:\\Qt\\Tools\\mingw1120_64\\x86_64-w64-mingw32\\include","-fmessage-length=0","-fdiagnostics-show-note-include-stack","-fretain-comments-from-system-headers","-fmacro-backtrace-limit=0","-ferror-limit=1000","-x","c++-header","D:\\Repos\\AlgoDemon\\external_src\\widgets\\viewportcontroller.h"],"directory":"D:/Repos/AlgoDemon/project/build-AlgoDemon-Desktop_Qt_6_4_2_MinGW_64_bit-Debug/.qtc_clangd","file":"D:/Repos/AlgoDemon/external_src/widgets/viewportcontroller.h"},{"arguments":["clang","-Wno-documentation-unknown-command","-Wno-unknown-warning-option","-Wno-unknown-pragmas","-nostdinc","-nostdinc++","-g","-std=gnu++2a","-Wall","-Wextra","-Wextra","-fexceptions","-mthreads","-fsyntax-only","-m64","--target=x86_64-w64-mingw32","-DUNICODE","-D_UNICODE","-DWIN32","-DMINGW_HAS_SECURE_API","-DQT_QML_DEBUG","-DQT_WIDGETS_LIB","-DQT_GUI_LIB","-DQT_CONCURRENT_LIB","-DQT_SERIALPORT_LIB","-DQT_CORE_LIB","-DQT_NEEDS_QMAIN","-DQ_CREATOR_RUN","-IC:\\Qt\\Tools\\QtCreator\\share\\qtcreator\\cplusplus\\wrappedMingwHeaders","-IC:\\Qt\\Tools\\QtCreator\\share\\qtcreator\\cplusplus\\wrappedQtHeaders","-IC:\\Qt\\Tools\\QtCreator\\share\\qtcreator\\cplusplus\\wrappedQtHeaders\\QtCore","-ID:\\Repos\\AlgoDemon\\project\\source","-ID:\\Repos\\AlgoDemon\\external_src","-ID:\\Repos\\AlgoDemon\\external_src\\external\\Qt-Advanced-Docking-System-master\\src","-ID:\\Repos\\AlgoDemon\\external_src\\camera_module\\include","-ID:\\Repos\\AlgoDemon\\external_src\\camera_module\\include\\CameraSDK_include","-IC:\\Qt\\6.4.2\\mingw_64\\include","-IC:\\Qt\\6.4.2\\mingw_64\\include\\QtWidgets","-IC:\\Qt\\6.4.2\\mingw_64\\include\\QtGui","-IC:\\Qt\\6.4.2\\mingw_64\\include\\QtConcurrent","-IC:\\Qt\\6.4.2\\mingw_64\\include\\QtSerialPort","-IC:\\Qt\\6.4.2\\mingw_64\\include\\QtCore","-ID:\\Repos\\AlgoDemon\\project\\build-AlgoDemon-Desktop_Qt_6_4_2_MinGW_64_bit-Debug\\debug","-ID:\\Repos\\AlgoDemon\\project\\build-AlgoDemon-Desktop_Qt_6_4_2_MinGW_64_bit-Debug","-IC:\\Qt\\6.4.2\\mingw_64\\mkspecs\\win32-g++","-isystem","C:\\Qt\\Tools\\mingw1120_64\\lib\\gcc\\x86_64-w64-mingw32\\11.2.0\\include\\c++","-isystem","C:\\Qt\\Tools\\mingw1120_64\\lib\\gcc\\x86_64-w64-mingw32\\11.2.0\\include\\c++\\x86_64-w64-mingw32","-isystem","C:\\Qt\\Tools\\mingw1120_64\\lib\\gcc\\x86_64-w64-mingw32\\11.2.0\\include\\c++\\backward","-isystem","C:\\Qt\\Tools\\QtCreator\\bin\\clang\\lib\\clang\\15.0.0\\include","-isystem","C:\\Qt\\Tools\\mingw1120_64\\x86_64-w64-mingw32\\include","-fmessage-length=0","-fdiagnostics-show-note-include-stack","-fretain-comments-from-system-headers","-fmacro-backtrace-limit=0","-ferror-limit=1000","-x","c++-header","D:\\Repos\\AlgoDemon\\external_src\\camera_module\\include\\autoexposurehandler.h"],"directory":"D:/Repos/AlgoDemon/project/build-AlgoDemon-Desktop_Qt_6_4_2_MinGW_64_bit-Debug/.qtc_clangd","file":"D:/Repos/AlgoDemon/external_src/camera_module/include/autoexposurehandler.h"},{"arguments":["clang","-Wno-documentation-unknown-command","-Wno-unknown-warning-option","-Wno-unknown-pragmas","-nostdinc","-nostdinc++","-g","-std=gnu++2a","-Wall","-Wextra","-Wextra","-fexceptions","-mthreads","-fsyntax-only","-m64","--target=x86_64-w64-mingw32","-DUNICODE","-D_UNICODE","-DWIN32","-DMINGW_HAS_SECURE_API","-DQT_QML_DEBUG","-DQT_WIDGETS_LIB","-DQT_GUI_LIB","-DQT_CONCURRENT_LIB","-DQT_SERIALPORT_LIB","-DQT_CORE_LIB","-DQT_NEEDS_QMAIN","-DQ_CREATOR_RUN","-IC:\\Qt\\Tools\\QtCreator\\share\\qtcreator\\cplusplus\\wrappedMingwHeaders","-IC:\\Qt\\Tools\\QtCreator\\share\\qtcreator\\cplusplus\\wrappedQtHeaders","-IC:\\Qt\\Tools\\QtCreator\\share\\qtcreator\\cplusplus\\wrappedQtHeaders\\QtCore","-ID:\\Repos\\AlgoDemon\\project\\source","-ID:\\Repos\\AlgoDemon\\external_src","-ID:\\Repos\\AlgoDemon\\external_src\\external\\Qt-Advanced-Docking-System-master\\src","-ID:\\Repos\\AlgoDemon\\external_src\\camera_module\\include","-ID:\\Repos\\AlgoDemon\\external_src\\camera_module\\include\\CameraSDK_include","-IC:\\Qt\\6.4.2\\mingw_64\\include","-IC:\\Qt\\6.4.2\\mingw_64\\include\\QtWidgets","-IC:\\Qt\\6.4.2\\mingw_64\\include\\QtGui","-IC:\\Qt\\6.4.2\\mingw_64\\include\\QtConcurrent","-IC:\\Qt\\6.4.2\\mingw_64\\include\\QtSerialPort","-IC:\\Qt\\6.4.2\\mingw_64\\include\\QtCore","-ID:\\Repos\\AlgoDemon\\project\\build-AlgoDemon-Desktop_Qt_6_4_2_MinGW_64_bit-Debug\\debug","-ID:\\Repos\\AlgoDemon\\project\\build-AlgoDemon-Desktop_Qt_6_4_2_MinGW_64_bit-Debug","-IC:\\Qt\\6.4.2\\mingw_64\\mkspecs\\win32-g++","-isystem","C:\\Qt\\Tools\\mingw1120_64\\lib\\gcc\\x86_64-w64-mingw32\\11.2.0\\include\\c++","-isystem","C:\\Qt\\Tools\\mingw1120_64\\lib\\gcc\\x86_64-w64-mingw32\\11.2.0\\include\\c++\\x86_64-w64-mingw32","-isystem","C:\\Qt\\Tools\\mingw1120_64\\lib\\gcc\\x86_64-w64-mingw32\\11.2.0\\include\\c++\\backward","-isystem","C:\\Qt\\Tools\\QtCreator\\bin\\clang\\lib\\clang\\15.0.0\\include","-isystem","C:\\Qt\\Tools\\mingw1120_64\\x86_64-w64-mingw32\\include","-fmessage-length=0","-fdiagnostics-show-note-include-stack","-fretain-comments-from-system-headers","-fmacro-backtrace-limit=0","-ferror-limit=1000","-x","c++-header","D:\\Repos\\AlgoDemon\\external_src\\camera_module\\include\\camenums.h"],"directory":"D:/Repos/AlgoDemon/project/build-AlgoDemon-Desktop_Qt_6_4_2_MinGW_64_bit-Debug/.qtc_clangd","file":"D:/Repos/AlgoDemon/external_src/camera_module/include/camenums.h"},{"arguments":["clang","-Wno-documentation-unknown-command","-Wno-unknown-warning-option","-Wno-unknown-pragmas","-nostdinc","-nostdinc++","-g","-std=gnu++2a","-Wall","-Wextra","-Wextra","-fexceptions","-mthreads","-fsyntax-only","-m64","--target=x86_64-w64-mingw32","-DUNICODE","-D_UNICODE","-DWIN32","-DMINGW_HAS_SECURE_API","-DQT_QML_DEBUG","-DQT_WIDGETS_LIB","-DQT_GUI_LIB","-DQT_CONCURRENT_LIB","-DQT_SERIALPORT_LIB","-DQT_CORE_LIB","-DQT_NEEDS_QMAIN","-DQ_CREATOR_RUN","-IC:\\Qt\\Tools\\QtCreator\\share\\qtcreator\\cplusplus\\wrappedMingwHeaders","-IC:\\Qt\\Tools\\QtCreator\\share\\qtcreator\\cplusplus\\wrappedQtHeaders","-IC:\\Qt\\Tools\\QtCreator\\share\\qtcreator\\cplusplus\\wrappedQtHeaders\\QtCore","-ID:\\Repos\\AlgoDemon\\project\\source","-ID:\\Repos\\AlgoDemon\\external_src","-ID:\\Repos\\AlgoDemon\\external_src\\external\\Qt-Advanced-Docking-System-master\\src","-ID:\\Repos\\AlgoDemon\\external_src\\camera_module\\include","-ID:\\Repos\\AlgoDemon\\external_src\\camera_module\\include\\CameraSDK_include","-IC:\\Qt\\6.4.2\\mingw_64\\include","-IC:\\Qt\\6.4.2\\mingw_64\\include\\QtWidgets","-IC:\\Qt\\6.4.2\\mingw_64\\include\\QtGui","-IC:\\Qt\\6.4.2\\mingw_64\\include\\QtConcurrent","-IC:\\Qt\\6.4.2\\mingw_64\\include\\QtSerialPort","-IC:\\Qt\\6.4.2\\mingw_64\\include\\QtCore","-ID:\\Repos\\AlgoDemon\\project\\build-AlgoDemon-Desktop_Qt_6_4_2_MinGW_64_bit-Debug\\debug","-ID:\\Repos\\AlgoDemon\\project\\build-AlgoDemon-Desktop_Qt_6_4_2_MinGW_64_bit-Debug","-IC:\\Qt\\6.4.2\\mingw_64\\mkspecs\\win32-g++","-isystem","C:\\Qt\\Tools\\mingw1120_64\\lib\\gcc\\x86_64-w64-mingw32\\11.2.0\\include\\c++","-isystem","C:\\Qt\\Tools\\mingw1120_64\\lib\\gcc\\x86_64-w64-mingw32\\11.2.0\\include\\c++\\x86_64-w64-mingw32","-isystem","C:\\Qt\\Tools\\mingw1120_64\\lib\\gcc\\x86_64-w64-mingw32\\11.2.0\\include\\c++\\backward","-isystem","C:\\Qt\\Tools\\QtCreator\\bin\\clang\\lib\\clang\\15.0.0\\include","-isystem","C:\\Qt\\Tools\\mingw1120_64\\x86_64-w64-mingw32\\include","-fmessage-length=0","-fdiagnostics-show-note-include-stack","-fretain-comments-from-system-headers","-fmacro-backtrace-limit=0","-ferror-limit=1000","-x","c++-header","D:\\Repos\\AlgoDemon\\external_src\\camera_module\\include\\cameraqhyccd.h"],"directory":"D:/Repos/AlgoDemon/project/build-AlgoDemon-Desktop_Qt_6_4_2_MinGW_64_bit-Debug/.qtc_clangd","file":"D:/Repos/AlgoDemon/external_src/camera_module/include/cameraqhyccd.h"},{"arguments":["clang","-Wno-documentation-unknown-command","-Wno-unknown-warning-option","-Wno-unknown-pragmas","-nostdinc","-nostdinc++","-g","-std=gnu++2a","-Wall","-Wextra","-Wextra","-fexceptions","-mthreads","-fsyntax-only","-m64","--target=x86_64-w64-mingw32","-DUNICODE","-D_UNICODE","-DWIN32","-DMINGW_HAS_SECURE_API","-DQT_QML_DEBUG","-DQT_WIDGETS_LIB","-DQT_GUI_LIB","-DQT_CONCURRENT_LIB","-DQT_SERIALPORT_LIB","-DQT_CORE_LIB","-DQT_NEEDS_QMAIN","-DQ_CREATOR_RUN","-IC:\\Qt\\Tools\\QtCreator\\share\\qtcreator\\cplusplus\\wrappedMingwHeaders","-IC:\\Qt\\Tools\\QtCreator\\share\\qtcreator\\cplusplus\\wrappedQtHeaders","-IC:\\Qt\\Tools\\QtCreator\\share\\qtcreator\\cplusplus\\wrappedQtHeaders\\QtCore","-ID:\\Repos\\AlgoDemon\\project\\source","-ID:\\Repos\\AlgoDemon\\external_src","-ID:\\Repos\\AlgoDemon\\external_src\\external\\Qt-Advanced-Docking-System-master\\src","-ID:\\Repos\\AlgoDemon\\external_src\\camera_module\\include","-ID:\\Repos\\AlgoDemon\\external_src\\camera_module\\include\\CameraSDK_include","-IC:\\Qt\\6.4.2\\mingw_64\\include","-IC:\\Qt\\6.4.2\\mingw_64\\include\\QtWidgets","-IC:\\Qt\\6.4.2\\mingw_64\\include\\QtGui","-IC:\\Qt\\6.4.2\\mingw_64\\include\\QtConcurrent","-IC:\\Qt\\6.4.2\\mingw_64\\include\\QtSerialPort","-IC:\\Qt\\6.4.2\\mingw_64\\include\\QtCore","-ID:\\Repos\\AlgoDemon\\project\\build-AlgoDemon-Desktop_Qt_6_4_2_MinGW_64_bit-Debug\\debug","-ID:\\Repos\\AlgoDemon\\project\\build-AlgoDemon-Desktop_Qt_6_4_2_MinGW_64_bit-Debug","-IC:\\Qt\\6.4.2\\mingw_64\\mkspecs\\win32-g++","-isystem","C:\\Qt\\Tools\\mingw1120_64\\lib\\gcc\\x86_64-w64-mingw32\\11.2.0\\include\\c++","-isystem","C:\\Qt\\Tools\\mingw1120_64\\lib\\gcc\\x86_64-w64-mingw32\\11.2.0\\include\\c++\\x86_64-w64-mingw32","-isystem","C:\\Qt\\Tools\\mingw1120_64\\lib\\gcc\\x86_64-w64-mingw32\\11.2.0\\include\\c++\\backward","-isystem","C:\\Qt\\Tools\\QtCreator\\bin\\clang\\lib\\clang\\15.0.0\\include","-isystem","C:\\Qt\\Tools\\mingw1120_64\\x86_64-w64-mingw32\\include","-fmessage-length=0","-fdiagnostics-show-note-include-stack","-fretain-comments-from-system-headers","-fmacro-backtrace-limit=0","-ferror-limit=1000","-x","c++-header","D:\\Repos\\AlgoDemon\\external_src\\camera_module\\include\\camframe.h"],"directory":"D:/Repos/AlgoDemon/project/build-AlgoDemon-Desktop_Qt_6_4_2_MinGW_64_bit-Debug/.qtc_clangd","file":"D:/Repos/AlgoDemon/external_src/camera_module/include/camframe.h"},{"arguments":["clang","-Wno-documentation-unknown-command","-Wno-unknown-warning-option","-Wno-unknown-pragmas","-nostdinc","-nostdinc++","-g","-std=gnu++2a","-Wall","-Wextra","-Wextra","-fexceptions","-mthreads","-fsyntax-only","-m64","--target=x86_64-w64-mingw32","-DUNICODE","-D_UNICODE","-DWIN32","-DMINGW_HAS_SECURE_API","-DQT_QML_DEBUG","-DQT_WIDGETS_LIB","-DQT_GUI_LIB","-DQT_CONCURRENT_LIB","-DQT_SERIALPORT_LIB","-DQT_CORE_LIB","-DQT_NEEDS_QMAIN","-DQ_CREATOR_RUN","-IC:\\Qt\\Tools\\QtCreator\\share\\qtcreator\\cplusplus\\wrappedMingwHeaders","-IC:\\Qt\\Tools\\QtCreator\\share\\qtcreator\\cplusplus\\wrappedQtHeaders","-IC:\\Qt\\Tools\\QtCreator\\share\\qtcreator\\cplusplus\\wrappedQtHeaders\\QtCore","-ID:\\Repos\\AlgoDemon\\project\\source","-ID:\\Repos\\AlgoDemon\\external_src","-ID:\\Repos\\AlgoDemon\\external_src\\external\\Qt-Advanced-Docking-System-master\\src","-ID:\\Repos\\AlgoDemon\\external_src\\camera_module\\include","-ID:\\Repos\\AlgoDemon\\external_src\\camera_module\\include\\CameraSDK_include","-IC:\\Qt\\6.4.2\\mingw_64\\include","-IC:\\Qt\\6.4.2\\mingw_64\\include\\QtWidgets","-IC:\\Qt\\6.4.2\\mingw_64\\include\\QtGui","-IC:\\Qt\\6.4.2\\mingw_64\\include\\QtConcurrent","-IC:\\Qt\\6.4.2\\mingw_64\\include\\QtSerialPort","-IC:\\Qt\\6.4.2\\mingw_64\\include\\QtCore","-ID:\\Repos\\AlgoDemon\\project\\build-AlgoDemon-Desktop_Qt_6_4_2_MinGW_64_bit-Debug\\debug","-ID:\\Repos\\AlgoDemon\\project\\build-AlgoDemon-Desktop_Qt_6_4_2_MinGW_64_bit-Debug","-IC:\\Qt\\6.4.2\\mingw_64\\mkspecs\\win32-g++","-isystem","C:\\Qt\\Tools\\mingw1120_64\\lib\\gcc\\x86_64-w64-mingw32\\11.2.0\\include\\c++","-isystem","C:\\Qt\\Tools\\mingw1120_64\\lib\\gcc\\x86_64-w64-mingw32\\11.2.0\\include\\c++\\x86_64-w64-mingw32","-isystem","C:\\Qt\\Tools\\mingw1120_64\\lib\\gcc\\x86_64-w64-mingw32\\11.2.0\\include\\c++\\backward","-isystem","C:\\Qt\\Tools\\QtCreator\\bin\\clang\\lib\\clang\\15.0.0\\include","-isystem","C:\\Qt\\Tools\\mingw1120_64\\x86_64-w64-mingw32\\include","-fmessage-length=0","-fdiagnostics-show-note-include-stack","-fretain-comments-from-system-headers","-fmacro-backtrace-limit=0","-ferror-limit=1000","-x","c++-header","D:\\Repos\\AlgoDemon\\external_src\\camera_module\\include\\camstruct.h"],"directory":"D:/Repos/AlgoDemon/project/build-AlgoDemon-Desktop_Qt_6_4_2_MinGW_64_bit-Debug/.qtc_clangd","file":"D:/Repos/AlgoDemon/external_src/camera_module/include/camstruct.h"},{"arguments":["clang","-Wno-documentation-unknown-command","-Wno-unknown-warning-option","-Wno-unknown-pragmas","-nostdinc","-nostdinc++","-g","-std=gnu++2a","-Wall","-Wextra","-Wextra","-fexceptions","-mthreads","-fsyntax-only","-m64","--target=x86_64-w64-mingw32","-DUNICODE","-D_UNICODE","-DWIN32","-DMINGW_HAS_SECURE_API","-DQT_QML_DEBUG","-DQT_WIDGETS_LIB","-DQT_GUI_LIB","-DQT_CONCURRENT_LIB","-DQT_SERIALPORT_LIB","-DQT_CORE_LIB","-DQT_NEEDS_QMAIN","-DQ_CREATOR_RUN","-IC:\\Qt\\Tools\\QtCreator\\share\\qtcreator\\cplusplus\\wrappedMingwHeaders","-IC:\\Qt\\Tools\\QtCreator\\share\\qtcreator\\cplusplus\\wrappedQtHeaders","-IC:\\Qt\\Tools\\QtCreator\\share\\qtcreator\\cplusplus\\wrappedQtHeaders\\QtCore","-ID:\\Repos\\AlgoDemon\\project\\source","-ID:\\Repos\\AlgoDemon\\external_src","-ID:\\Repos\\AlgoDemon\\external_src\\external\\Qt-Advanced-Docking-System-master\\src","-ID:\\Repos\\AlgoDemon\\external_src\\camera_module\\include","-ID:\\Repos\\AlgoDemon\\external_src\\camera_module\\include\\CameraSDK_include","-IC:\\Qt\\6.4.2\\mingw_64\\include","-IC:\\Qt\\6.4.2\\mingw_64\\include\\QtWidgets","-IC:\\Qt\\6.4.2\\mingw_64\\include\\QtGui","-IC:\\Qt\\6.4.2\\mingw_64\\include\\QtConcurrent","-IC:\\Qt\\6.4.2\\mingw_64\\include\\QtSerialPort","-IC:\\Qt\\6.4.2\\mingw_64\\include\\QtCore","-ID:\\Repos\\AlgoDemon\\project\\build-AlgoDemon-Desktop_Qt_6_4_2_MinGW_64_bit-Debug\\debug","-ID:\\Repos\\AlgoDemon\\project\\build-AlgoDemon-Desktop_Qt_6_4_2_MinGW_64_bit-Debug","-IC:\\Qt\\6.4.2\\mingw_64\\mkspecs\\win32-g++","-isystem","C:\\Qt\\Tools\\mingw1120_64\\lib\\gcc\\x86_64-w64-mingw32\\11.2.0\\include\\c++","-isystem","C:\\Qt\\Tools\\mingw1120_64\\lib\\gcc\\x86_64-w64-mingw32\\11.2.0\\include\\c++\\x86_64-w64-mingw32","-isystem","C:\\Qt\\Tools\\mingw1120_64\\lib\\gcc\\x86_64-w64-mingw32\\11.2.0\\include\\c++\\backward","-isystem","C:\\Qt\\Tools\\QtCreator\\bin\\clang\\lib\\clang\\15.0.0\\include","-isystem","C:\\Qt\\Tools\\mingw1120_64\\x86_64-w64-mingw32\\include","-fmessage-length=0","-fdiagnostics-show-note-include-stack","-fretain-comments-from-system-headers","-fmacro-backtrace-limit=0","-ferror-limit=1000","-x","c++-header","D:\\Repos\\AlgoDemon\\external_src\\camera_module\\include\\framepipeline.h"],"directory":"D:/Repos/AlgoDemon/project/build-AlgoDemon-Desktop_Qt_6_4_2_MinGW_64_bit-Debug/.qtc_clangd","file":"D:/Repos/AlgoDemon/external_src/camera_module/include/framepipeline.h"},{"arguments":["clang","-Wno-documentation-unknown-command","-Wno-unknown-warning-option","-Wno-unknown-pragmas","-nostdinc","-nostdinc++","-g","-std=gnu++2a","-Wall","-Wextra","-Wextra","-fexceptions","-mthreads","-fsyntax-only","-m64","--target=x86_64-w64-mingw32","-DUNICODE","-D_UNICODE","-DWIN32","-DMINGW_HAS_SECURE_API","-DQT_QML_DEBUG","-DQT_WIDGETS_LIB","-DQT_GUI_LIB","-DQT_CONCURRENT_LIB","-DQT_SERIALPORT_LIB","-DQT_CORE_LIB","-DQT_NEEDS_QMAIN","-DQ_CREATOR_RUN","-IC:\\Qt\\Tools\\QtCreator\\share\\qtcreator\\cplusplus\\wrappedMingwHeaders","-IC:\\Qt\\Tools\\QtCreator\\share\\qtcreator\\cplusplus\\wrappedQtHeaders","-IC:\\Qt\\Tools\\QtCreator\\share\\qtcreator\\cplusplus\\wrappedQtHeaders\\QtCore","-ID:\\Repos\\AlgoDemon\\project\\source","-ID:\\Repos\\AlgoDemon\\external_src","-ID:\\Repos\\AlgoDemon\\external_src\\external\\Qt-Advanced-Docking-System-master\\src","-ID:\\Repos\\AlgoDemon\\external_src\\camera_module\\include","-ID:\\Repos\\AlgoDemon\\external_src\\camera_module\\include\\CameraSDK_include","-IC:\\Qt\\6.4.2\\mingw_64\\include","-IC:\\Qt\\6.4.2\\mingw_64\\include\\QtWidgets","-IC:\\Qt\\6.4.2\\mingw_64\\include\\QtGui","-IC:\\Qt\\6.4.2\\mingw_64\\include\\QtConcurrent","-IC:\\Qt\\6.4.2\\mingw_64\\include\\QtSerialPort","-IC:\\Qt\\6.4.2\\mingw_64\\include\\QtCore","-ID:\\Repos\\AlgoDemon\\project\\build-AlgoDemon-Desktop_Qt_6_4_2_MinGW_64_bit-Debug\\debug","-ID:\\Repos\\AlgoDemon\\project\\build-AlgoDemon-Desktop_Qt_6_4_2_MinGW_64_bit-Debug","-IC:\\Qt\\6.4.2\\mingw_64\\mkspecs\\win32-g++","-isystem","C:\\Qt\\Tools\\mingw1120_64\\lib\\gcc\\x86_64-w64-mingw32\\11.2.0\\include\\c++","-isystem","C:\\Qt\\Tools\\mingw1120_64\\lib\\gcc\\x86_64-w64-mingw32\\11.2.0\\include\\c++\\x86_64-w64-mingw32","-isystem","C:\\Qt\\Tools\\mingw1120_64\\lib\\gcc\\x86_64-w64-mingw32\\11.2.0\\include\\c++\\backward","-isystem","C:\\Qt\\Tools\\QtCreator\\bin\\clang\\lib\\clang\\15.0.0\\include","-isystem","C:\\Qt\\Tools\\mingw1120_64\\x86_64-w64-mingw32\\include","-fmessage-length=0","-fdiagnostics-show-note-include-stack","-fretain-comments-from-system-headers","-fmacro-backtrace-limit=0","-ferror-limit=1000","-x","c++-header","D:\\Repos\\AlgoDemon\\external_src\\camera_module\\include\\imageblurmetric.h"],"directory":"D:/Repos/AlgoDemon/project/build-AlgoDemon-Desktop_Qt_6_4_2_MinGW_64_bit-Debug/.qtc_clangd","file":"D:/Repos/AlgoDemon/external_src/camera_module/include/imageblurmetric.h"},{"arguments":["clang","-Wno-documentation-unknown-command","-Wno-unknown-warning-option","-Wno-unknown-pragmas","-nostdinc","-nostdinc++","-g","-std=gnu++2a","-Wall","-Wextra","-Wextra","-fexceptions","-mthreads","-fsyntax-only","-m64","--target=x86_64-w64-mingw32","-DUNICODE","-D_UNICODE","-DWIN32","-DMINGW_HAS_SECURE_API","-DQT_QML_DEBUG","-DQT_WIDGETS_LIB","-DQT_GUI_LIB","-DQT_CONCURRENT_LIB","-DQT_SERIALPORT_LIB","-DQT_CORE_LIB","-DQT_NEEDS_QMAIN","-DQ_CREATOR_RUN","-IC:\\Qt\\Tools\\QtCreator\\share\\qtcreator\\cplusplus\\wrappedMingwHeaders","-IC:\\Qt\\Tools\\QtCreator\\share\\qtcreator\\cplusplus\\wrappedQtHeaders","-IC:\\Qt\\Tools\\QtCreator\\share\\qtcreator\\cplusplus\\wrappedQtHeaders\\QtCore","-ID:\\Repos\\AlgoDemon\\project\\source","-ID:\\Repos\\AlgoDemon\\external_src","-ID:\\Repos\\AlgoDemon\\external_src\\external\\Qt-Advanced-Docking-System-master\\src","-ID:\\Repos\\AlgoDemon\\external_src\\camera_module\\include","-ID:\\Repos\\AlgoDemon\\external_src\\camera_module\\include\\CameraSDK_include","-IC:\\Qt\\6.4.2\\mingw_64\\include","-IC:\\Qt\\6.4.2\\mingw_64\\include\\QtWidgets","-IC:\\Qt\\6.4.2\\mingw_64\\include\\QtGui","-IC:\\Qt\\6.4.2\\mingw_64\\include\\QtConcurrent","-IC:\\Qt\\6.4.2\\mingw_64\\include\\QtSerialPort","-IC:\\Qt\\6.4.2\\mingw_64\\include\\QtCore","-ID:\\Repos\\AlgoDemon\\project\\build-AlgoDemon-Desktop_Qt_6_4_2_MinGW_64_bit-Debug\\debug","-ID:\\Repos\\AlgoDemon\\project\\build-AlgoDemon-Desktop_Qt_6_4_2_MinGW_64_bit-Debug","-IC:\\Qt\\6.4.2\\mingw_64\\mkspecs\\win32-g++","-isystem","C:\\Qt\\Tools\\mingw1120_64\\lib\\gcc\\x86_64-w64-mingw32\\11.2.0\\include\\c++","-isystem","C:\\Qt\\Tools\\mingw1120_64\\lib\\gcc\\x86_64-w64-mingw32\\11.2.0\\include\\c++\\x86_64-w64-mingw32","-isystem","C:\\Qt\\Tools\\mingw1120_64\\lib\\gcc\\x86_64-w64-mingw32\\11.2.0\\include\\c++\\backward","-isystem","C:\\Qt\\Tools\\QtCreator\\bin\\clang\\lib\\clang\\15.0.0\\include","-isystem","C:\\Qt\\Tools\\mingw1120_64\\x86_64-w64-mingw32\\include","-fmessage-length=0","-fdiagnostics-show-note-include-stack","-fretain-comments-from-system-headers","-fmacro-backtrace-limit=0","-ferror-limit=1000","-x","c++-header","D:\\Repos\\AlgoDemon\\external_src\\camera_module\\include\\imageprocess.h"],"directory":"D:/Repos/AlgoDemon/project/build-AlgoDemon-Desktop_Qt_6_4_2_MinGW_64_bit-Debug/.qtc_clangd","file":"D:/Repos/AlgoDemon/external_src/camera_module/include/imageprocess.h"},{"arguments":["clang","-Wno-documentation-unknown-command","-Wno-unknown-warning-option","-Wno-unknown-pragmas","-nostdinc","-nostdinc++","-g","-std=gnu++2a","-Wall","-Wextra","-Wextra","-fexceptions","-mthreads","-fsyntax-only","-m64","--target=x86_64-w64-mingw32","-DUNICODE","-D_UNICODE","-DWIN32","-DMINGW_HAS_SECURE_API","-DQT_QML_DEBUG","-DQT_WIDGETS_LIB","-DQT_GUI_LIB","-DQT_CONCURRENT_LIB","-DQT_SERIALPORT_LIB","-DQT_CORE_LIB","-DQT_NEEDS_QMAIN","-DQ_CREATOR_RUN","-IC:\\Qt\\Tools\\QtCreator\\share\\qtcreator\\cplusplus\\wrappedMingwHeaders","-IC:\\Qt\\Tools\\QtCreator\\share\\qtcreator\\cplusplus\\wrappedQtHeaders","-IC:\\Qt\\Tools\\QtCreator\\share\\qtcreator\\cplusplus\\wrappedQtHeaders\\QtCore","-ID:\\Repos\\AlgoDemon\\project\\source","-ID:\\Repos\\AlgoDemon\\external_src","-ID:\\Repos\\AlgoDemon\\external_src\\external\\Qt-Advanced-Docking-System-master\\src","-ID:\\Repos\\AlgoDemon\\external_src\\camera_module\\include","-ID:\\Repos\\AlgoDemon\\external_src\\camera_module\\include\\CameraSDK_include","-IC:\\Qt\\6.4.2\\mingw_64\\include","-IC:\\Qt\\6.4.2\\mingw_64\\include\\QtWidgets","-IC:\\Qt\\6.4.2\\mingw_64\\include\\QtGui","-IC:\\Qt\\6.4.2\\mingw_64\\include\\QtConcurrent","-IC:\\Qt\\6.4.2\\mingw_64\\include\\QtSerialPort","-IC:\\Qt\\6.4.2\\mingw_64\\include\\QtCore","-ID:\\Repos\\AlgoDemon\\project\\build-AlgoDemon-Desktop_Qt_6_4_2_MinGW_64_bit-Debug\\debug","-ID:\\Repos\\AlgoDemon\\project\\build-AlgoDemon-Desktop_Qt_6_4_2_MinGW_64_bit-Debug","-IC:\\Qt\\6.4.2\\mingw_64\\mkspecs\\win32-g++","-isystem","C:\\Qt\\Tools\\mingw1120_64\\lib\\gcc\\x86_64-w64-mingw32\\11.2.0\\include\\c++","-isystem","C:\\Qt\\Tools\\mingw1120_64\\lib\\gcc\\x86_64-w64-mingw32\\11.2.0\\include\\c++\\x86_64-w64-mingw32","-isystem","C:\\Qt\\Tools\\mingw1120_64\\lib\\gcc\\x86_64-w64-mingw32\\11.2.0\\include\\c++\\backward","-isystem","C:\\Qt\\Tools\\QtCreator\\bin\\clang\\lib\\clang\\15.0.0\\include","-isystem","C:\\Qt\\Tools\\mingw1120_64\\x86_64-w64-mingw32\\include","-fmessage-length=0","-fdiagnostics-show-note-include-stack","-fretain-comments-from-system-headers","-fmacro-backtrace-limit=0","-ferror-limit=1000","-x","c++-header","D:\\Repos\\AlgoDemon\\external_src\\camera_module\\include\\objectivecontroller.h"],"directory":"D:/Repos/AlgoDemon/project/build-AlgoDemon-Desktop_Qt_6_4_2_MinGW_64_bit-Debug/.qtc_clangd","file":"D:/Repos/AlgoDemon/external_src/camera_module/include/objectivecontroller.h"},{"arguments":["clang","-Wno-documentation-unknown-command","-Wno-unknown-warning-option","-Wno-unknown-pragmas","-nostdinc","-nostdinc++","-g","-std=gnu++2a","-Wall","-Wextra","-Wextra","-fexceptions","-mthreads","-fsyntax-only","-m64","--target=x86_64-w64-mingw32","-DUNICODE","-D_UNICODE","-DWIN32","-DMINGW_HAS_SECURE_API","-DQT_QML_DEBUG","-DQT_WIDGETS_LIB","-DQT_GUI_LIB","-DQT_CONCURRENT_LIB","-DQT_SERIALPORT_LIB","-DQT_CORE_LIB","-DQT_NEEDS_QMAIN","-DQ_CREATOR_RUN","-IC:\\Qt\\Tools\\QtCreator\\share\\qtcreator\\cplusplus\\wrappedMingwHeaders","-IC:\\Qt\\Tools\\QtCreator\\share\\qtcreator\\cplusplus\\wrappedQtHeaders","-IC:\\Qt\\Tools\\QtCreator\\share\\qtcreator\\cplusplus\\wrappedQtHeaders\\QtCore","-ID:\\Repos\\AlgoDemon\\project\\source","-ID:\\Repos\\AlgoDemon\\external_src","-ID:\\Repos\\AlgoDemon\\external_src\\external\\Qt-Advanced-Docking-System-master\\src","-ID:\\Repos\\AlgoDemon\\external_src\\camera_module\\include","-ID:\\Repos\\AlgoDemon\\external_src\\camera_module\\include\\CameraSDK_include","-IC:\\Qt\\6.4.2\\mingw_64\\include","-IC:\\Qt\\6.4.2\\mingw_64\\include\\QtWidgets","-IC:\\Qt\\6.4.2\\mingw_64\\include\\QtGui","-IC:\\Qt\\6.4.2\\mingw_64\\include\\QtConcurrent","-IC:\\Qt\\6.4.2\\mingw_64\\include\\QtSerialPort","-IC:\\Qt\\6.4.2\\mingw_64\\include\\QtCore","-ID:\\Repos\\AlgoDemon\\project\\build-AlgoDemon-Desktop_Qt_6_4_2_MinGW_64_bit-Debug\\debug","-ID:\\Repos\\AlgoDemon\\project\\build-AlgoDemon-Desktop_Qt_6_4_2_MinGW_64_bit-Debug","-IC:\\Qt\\6.4.2\\mingw_64\\mkspecs\\win32-g++","-isystem","C:\\Qt\\Tools\\mingw1120_64\\lib\\gcc\\x86_64-w64-mingw32\\11.2.0\\include\\c++","-isystem","C:\\Qt\\Tools\\mingw1120_64\\lib\\gcc\\x86_64-w64-mingw32\\11.2.0\\include\\c++\\x86_64-w64-mingw32","-isystem","C:\\Qt\\Tools\\mingw1120_64\\lib\\gcc\\x86_64-w64-mingw32\\11.2.0\\include\\c++\\backward","-isystem","C:\\Qt\\Tools\\QtCreator\\bin\\clang\\lib\\clang\\15.0.0\\include","-isystem","C:\\Qt\\Tools\\mingw1120_64\\x86_64-w64-mingw32\\include","-fmessage-length=0","-fdiagnostics-show-note-include-stack","-fretain-comments-from-system-headers","-fmacro-backtrace-limit=0","-ferror-limit=1000","-x","c++-header","D:\\Repos\\AlgoDemon\\external_src\\camera_module\\include\\serialib.h"],"directory":"D:/Repos/AlgoDemon/project/build-AlgoDemon-Desktop_Qt_6_4_2_MinGW_64_bit-Debug/.qtc_clangd","file":"D:/Repos/AlgoDemon/external_src/camera_module/include/serialib.h"},{"arguments":["clang","-Wno-documentation-unknown-command","-Wno-unknown-warning-option","-Wno-unknown-pragmas","-nostdinc","-nostdinc++","-g","-std=gnu++2a","-Wall","-Wextra","-Wextra","-fexceptions","-mthreads","-fsyntax-only","-m64","--target=x86_64-w64-mingw32","-DUNICODE","-D_UNICODE","-DWIN32","-DMINGW_HAS_SECURE_API","-DQT_QML_DEBUG","-DQT_WIDGETS_LIB","-DQT_GUI_LIB","-DQT_CONCURRENT_LIB","-DQT_SERIALPORT_LIB","-DQT_CORE_LIB","-DQT_NEEDS_QMAIN","-DQ_CREATOR_RUN","-IC:\\Qt\\Tools\\QtCreator\\share\\qtcreator\\cplusplus\\wrappedMingwHeaders","-IC:\\Qt\\Tools\\QtCreator\\share\\qtcreator\\cplusplus\\wrappedQtHeaders","-IC:\\Qt\\Tools\\QtCreator\\share\\qtcreator\\cplusplus\\wrappedQtHeaders\\QtCore","-ID:\\Repos\\AlgoDemon\\project\\source","-ID:\\Repos\\AlgoDemon\\external_src","-ID:\\Repos\\AlgoDemon\\external_src\\external\\Qt-Advanced-Docking-System-master\\src","-ID:\\Repos\\AlgoDemon\\external_src\\camera_module\\include","-ID:\\Repos\\AlgoDemon\\external_src\\camera_module\\include\\CameraSDK_include","-IC:\\Qt\\6.4.2\\mingw_64\\include","-IC:\\Qt\\6.4.2\\mingw_64\\include\\QtWidgets","-IC:\\Qt\\6.4.2\\mingw_64\\include\\QtGui","-IC:\\Qt\\6.4.2\\mingw_64\\include\\QtConcurrent","-IC:\\Qt\\6.4.2\\mingw_64\\include\\QtSerialPort","-IC:\\Qt\\6.4.2\\mingw_64\\include\\QtCore","-ID:\\Repos\\AlgoDemon\\project\\build-AlgoDemon-Desktop_Qt_6_4_2_MinGW_64_bit-Debug\\debug","-ID:\\Repos\\AlgoDemon\\project\\build-AlgoDemon-Desktop_Qt_6_4_2_MinGW_64_bit-Debug","-IC:\\Qt\\6.4.2\\mingw_64\\mkspecs\\win32-g++","-isystem","C:\\Qt\\Tools\\mingw1120_64\\lib\\gcc\\x86_64-w64-mingw32\\11.2.0\\include\\c++","-isystem","C:\\Qt\\Tools\\mingw1120_64\\lib\\gcc\\x86_64-w64-mingw32\\11.2.0\\include\\c++\\x86_64-w64-mingw32","-isystem","C:\\Qt\\Tools\\mingw1120_64\\lib\\gcc\\x86_64-w64-mingw32\\11.2.0\\include\\c++\\backward","-isystem","C:\\Qt\\Tools\\QtCreator\\bin\\clang\\lib\\clang\\15.0.0\\include","-isystem","C:\\Qt\\Tools\\mingw1120_64\\x86_64-w64-mingw32\\include","-fmessage-length=0","-fdiagnostics-show-note-include-stack","-fretain-comments-from-system-headers","-fmacro-backtrace-limit=0","-ferror-limit=1000","-x","c++-header","D:\\Repos\\AlgoDemon\\project\\build-AlgoDemon-Desktop_Qt_6_4_2_MinGW_64_bit-Debug\\ui_mainwindow.h"],"directory":"D:/Repos/AlgoDemon/project/build-AlgoDemon-Desktop_Qt_6_4_2_MinGW_64_bit-Debug/.qtc_clangd","file":"D:/Repos/AlgoDemon/project/build-AlgoDemon-Desktop_Qt_6_4_2_MinGW_64_bit-Debug/ui_mainwindow.h"}]